{"v":"4.8.0","meta":{"g":"LottieFiles AE 3.1.1","a":"","k":"","d":"","tc":""},"fr":24,"ip":0,"op":77,"w":1125,"h":400,"nm":"[Fin][60/40]우정지수_3배수","ddd":0,"assets":[{"id":"comp_0","layers":[{"ddd":0,"ind":2,"ty":3,"nm":"C_R","parent":22,"sr":1,"ks":{"o":{"a":0,"k":0,"ix":11},"r":{"a":0,"k":0,"ix":10},"p":{"a":1,"k":[{"i":{"x":0.446,"y":1},"o":{"x":0.578,"y":0},"t":0,"s":[166.25,18.625,0],"to":[0,0,0],"ti":[0,0,0]},{"i":{"x":0.451,"y":1},"o":{"x":0.604,"y":0},"t":29,"s":[152.75,7.625,0],"to":[0,0,0],"ti":[0,0,0]},{"i":{"x":0.306,"y":1},"o":{"x":0.477,"y":0},"t":61,"s":[177.25,-22.875,0],"to":[0,0,0],"ti":[0,0,0]},{"t":76,"s":[159.25,3.625,0]}],"ix":2},"a":{"a":0,"k":[50,50,0],"ix":1},"s":{"a":0,"k":[100,100,100],"ix":6}},"ao":0,"ip":0,"op":480,"st":0,"bm":0},{"ddd":0,"ind":3,"ty":4,"nm":"Smile 1","parent":2,"sr":1,"ks":{"o":{"a":0,"k":100,"ix":11},"r":{"a":0,"k":0,"ix":10},"p":{"a":0,"k":[31.446,49.819,0],"ix":2},"a":{"a":0,"k":[73.078,25.801,0],"ix":1},"s":{"a":0,"k":[100,100,100],"ix":6}},"ao":0,"shapes":[{"ty":"gr","it":[{"ind":0,"ty":"sh","ix":1,"ks":{"a":0,"k":{"i":[[9.458,-0.185],[15.503,6.727],[2.605,3.202],[1.021,8.12],[-3.93,0.491],[-0.574,-0.014],[-0.921,-6.046],[-7.875,-6.45],[-1.056,-0.466],[-14.347,-1.401],[-10.537,5.619],[-4.895,7.771],[-2.181,7.084],[-1.448,0.069],[-2.226,0.127],[0.651,-1.96],[11.355,-9.421],[8.379,-2.291]],"o":[[-17.503,-1.315],[-3.969,-1.722],[-5.08,-6.247],[-0.471,-3.743],[0.577,-0.072],[5.511,0.133],[1.527,10.016],[0.887,0.727],[13.204,5.827],[11.924,1.164],[8.028,-4.281],[3.935,-6.25],[0.43,-1.396],[2.227,-0.105],[2.033,-0.116],[-4.588,13.813],[-6.998,5.806],[-9.816,2.684]],"v":[[-4.13,25.486],[-53.277,13.35],[-62.846,5.458],[-72.397,-16.012],[-68.954,-20.243],[-67.225,-20.463],[-60.685,-15.213],[-46.113,9.501],[-43.112,11.26],[-1.781,22.363],[32.284,15.693],[51.52,-2.952],[60.948,-22.848],[63.655,-25.02],[70.333,-25.395],[72.233,-22.74],[48.988,12.406],[25.273,22.827]],"c":true},"ix":2},"nm":"Path 1","mn":"ADBE Vector Shape - Group","hd":false},{"ty":"fl","c":{"a":0,"k":[0.141176470588,0.141176470588,0.141176470588,1],"ix":4},"o":{"a":0,"k":100,"ix":5},"r":1,"bm":0,"nm":"Fill 1","mn":"ADBE Vector Graphic - Fill","hd":false},{"ty":"tr","p":{"a":0,"k":[73.134,25.76],"ix":2},"a":{"a":0,"k":[0,0],"ix":1},"s":{"a":0,"k":[100,100],"ix":3},"r":{"a":0,"k":0,"ix":6},"o":{"a":0,"k":100,"ix":7},"sk":{"a":0,"k":0,"ix":4},"sa":{"a":0,"k":0,"ix":5},"nm":"Transform"}],"nm":"Group 1","np":2,"cix":2,"bm":0,"ix":1,"mn":"ADBE Vector Group","hd":false}],"ip":66,"op":480,"st":0,"bm":0},{"ddd":0,"ind":4,"ty":4,"nm":"Smile 9","parent":2,"sr":1,"ks":{"o":{"a":0,"k":100,"ix":11},"r":{"a":0,"k":8.394,"ix":10},"p":{"a":0,"k":[28.181,49.888,0],"ix":2},"a":{"a":0,"k":[58.185,28.08,0],"ix":1},"s":{"a":0,"k":[100,100,100],"ix":6}},"ao":0,"shapes":[{"ty":"gr","it":[{"ind":0,"ty":"sh","ix":1,"ks":{"a":0,"k":{"i":[[0,0],[1.143,-1.406],[6.49,-3.526],[8.885,0.907],[1.043,-0.018],[5.503,1.405],[0.51,0.365],[3.164,1.453],[0.621,0.311],[3.027,7.2],[-2.867,1.347],[-10.96,2.688],[-11.765,1.246],[-8.159,0.787]],"o":[[-0.819,1.616],[-4.682,5.758],[-7.565,4.112],[-1.033,-0.105],[-5.812,0.099],[-0.599,-0.153],[-2.844,-2.038],[-0.605,-0.344],[-6.972,-3.49],[-1.214,-2.889],[10.277,-4.83],[11.495,-2.82],[8.153,-0.864],[0,0]],"v":[[43.999,-0.093],[41.046,4.432],[24.047,18.004],[-0.143,24.452],[-3.273,24.441],[-19.947,21.022],[-21.594,20.133],[-30.74,15.146],[-32.604,14.213],[-47.71,-1.753],[-45.697,-6.514],[-13.348,-16.302],[21.743,-22.065],[46.222,-24.424]],"c":true},"ix":2},"nm":"Path 1","mn":"ADBE Vector Shape - Group","hd":false},{"ind":1,"ty":"sh","ix":2,"ks":{"a":0,"k":{"i":[[-0.089,6.738],[1.764,0.119],[6.572,-0.538],[12.015,-1.801],[5.419,-1.497],[1.343,-0.305],[4.941,-1.865],[0,0],[1.469,-0.396],[5.677,-1.645],[-0.148,-0.641],[-6.885,-4.651],[-4.05,-2.839],[-6.677,-1.204],[-6.543,0.01],[-3.164,1.076],[-8.093,7.642],[-2.231,5.584]],"o":[[0.024,-1.817],[-6.641,-0.448],[-12.108,0.99],[-5.539,0.83],[-1.352,0.264],[-5.112,1.164],[0,0],[-1.541,0.15],[-5.719,1.539],[-0.683,0.198],[1.903,8.212],[4.106,2.774],[5.867,4.113],[6.424,1.159],[3.332,-0.005],[10.433,-3.549],[4.37,-4.127],[2.596,-6.499]],"v":[[57.657,-24.996],[55.21,-27.483],[35.428,-26.488],[-0.779,-22.366],[-17.273,-19.037],[-21.327,-18.239],[-36.609,-14.527],[-36.609,-14.527],[-40.997,-13.264],[-57.408,-6.768],[-57.869,-5.437],[-44.331,13.604],[-31.318,20.648],[-11.844,26.772],[7.761,27.128],[17.663,25.9],[45.869,9.749],[55.494,-4.993]],"c":true},"ix":2},"nm":"Path 2","mn":"ADBE Vector Shape - Group","hd":false},{"ty":"mm","mm":1,"nm":"Merge Paths 1","mn":"ADBE Vector Filter - Merge","hd":false},{"ty":"fl","c":{"a":0,"k":[0.141176470588,0.141176470588,0.141176470588,1],"ix":4},"o":{"a":0,"k":100,"ix":5},"r":1,"bm":0,"nm":"Fill 1","mn":"ADBE Vector Graphic - Fill","hd":false},{"ty":"tr","p":{"a":0,"k":[58.34,28.181],"ix":2},"a":{"a":0,"k":[0,0],"ix":1},"s":{"a":0,"k":[100,100],"ix":3},"r":{"a":0,"k":0,"ix":6},"o":{"a":0,"k":100,"ix":7},"sk":{"a":0,"k":0,"ix":4},"sa":{"a":0,"k":0,"ix":5},"nm":"Transform"}],"nm":"Group 1","np":4,"cix":2,"bm":0,"ix":1,"mn":"ADBE Vector Group","hd":false}],"ip":43,"op":66,"st":0,"bm":0},{"ddd":0,"ind":5,"ty":4,"nm":"Eyes_R 4","parent":2,"sr":1,"ks":{"o":{"a":0,"k":100,"ix":11},"r":{"a":0,"k":0,"ix":10},"p":{"a":0,"k":[31.338,-4.758,0],"ix":2},"a":{"a":0,"k":[65.014,21.585,0],"ix":1},"s":{"a":0,"k":[100,100,100],"ix":6}},"ao":0,"shapes":[{"ty":"gr","it":[{"ty":"gr","it":[{"ind":0,"ty":"sh","ix":1,"ks":{"a":0,"k":{"i":[[-0.682,0.847],[-0.083,0.287],[-0.224,1.719],[-1.046,0.155],[-4.852,-3.328],[-0.171,-1.337],[0.074,-3.402],[4.955,-0.332],[3.481,-0.066],[0.393,1.53],[0.021,3.197]],"o":[[0.083,-0.283],[0.295,-1.714],[0.158,-1.199],[5.332,-0.793],[1.114,0.764],[0.438,3.424],[-1.449,3.639],[-3.483,0.234],[-1.504,0.028],[-0.84,-3.262],[0.534,-0.866]],"v":[[-9.636,-2.618],[-9.387,-3.472],[-8.522,-8.608],[-6.608,-10.706],[8.867,-8.686],[10.645,-5.879],[10.597,4.34],[2.789,11.593],[-7.647,11.986],[-10.243,9.742],[-9.995,0.143]],"c":true},"ix":2},"nm":"Path 1","mn":"ADBE Vector Shape - Group","hd":false},{"ty":"fl","c":{"a":0,"k":[0.141176470588,0.141176470588,0.141176470588,1],"ix":4},"o":{"a":0,"k":100,"ix":5},"r":1,"bm":0,"nm":"Fill 1","mn":"ADBE Vector Graphic - Fill","hd":false},{"ty":"tr","p":{"a":1,"k":[{"i":{"x":0.42,"y":1},"o":{"x":0.268,"y":0.935},"t":43,"s":[95.49,22.784],"to":[-0.083,0.125],"ti":[0,0]},{"i":{"x":0.306,"y":1},"o":{"x":0.477,"y":0},"t":61,"s":[94.99,23.534],"to":[0,0],"ti":[-0.083,0.125]},{"t":73,"s":[95.49,22.784]}],"ix":2},"a":{"a":0,"k":[0,0],"ix":1},"s":{"a":0,"k":[100,100],"ix":3},"r":{"a":0,"k":0,"ix":6},"o":{"a":0,"k":100,"ix":7},"sk":{"a":0,"k":0,"ix":4},"sa":{"a":0,"k":0,"ix":5},"nm":"Transform"}],"nm":"Group 1","np":2,"cix":2,"bm":0,"ix":1,"mn":"ADBE Vector Group","hd":false},{"ty":"gr","it":[{"ind":0,"ty":"sh","ix":1,"ks":{"a":0,"k":{"i":[[-1.662,-1.997],[2.933,-5.513],[2.264,-3.012],[4.758,-0.112],[4.004,1.124],[3.043,1.641],[0.482,3.073],[0.314,1.248],[-2.396,5.289],[-1.999,0.769],[-5.406,-0.089],[-1.173,-0.395],[-1.191,-0.905]],"o":[[3.15,3.784],[-1.727,3.246],[-2.512,3.345],[-3.933,0.092],[-3.497,-0.981],[-2.877,-1.551],[-0.199,-1.272],[-1.517,-6.016],[0.905,-1.999],[5.089,-1.957],[1.238,0.02],[1.417,0.479],[2.146,1.628]],"v":[[18.198,-11.021],[19.945,2.791],[14.663,12.489],[5.072,18.927],[-6.621,18.328],[-15.969,13.863],[-20.626,6.776],[-21.36,2.981],[-18.415,-13.738],[-13.432,-17.495],[4.785,-19.232],[8.45,-18.742],[12.277,-16.439]],"c":true},"ix":2},"nm":"Path 1","mn":"ADBE Vector Shape - Group","hd":false},{"ty":"fl","c":{"a":0,"k":[1,1,1,1],"ix":4},"o":{"a":0,"k":100,"ix":5},"r":1,"bm":0,"nm":"Fill 1","mn":"ADBE Vector Graphic - Fill","hd":false},{"ty":"tr","p":{"a":0,"k":[106.767,19.702],"ix":2},"a":{"a":0,"k":[0,0],"ix":1},"s":{"a":0,"k":[100,100],"ix":3},"r":{"a":0,"k":0,"ix":6},"o":{"a":0,"k":100,"ix":7},"sk":{"a":0,"k":0,"ix":4},"sa":{"a":0,"k":0,"ix":5},"nm":"Transform"}],"nm":"Group 3","np":2,"cix":2,"bm":0,"ix":2,"mn":"ADBE Vector Group","hd":false},{"ty":"tr","p":{"a":0,"k":[106.583,19.607],"ix":2},"a":{"a":0,"k":[106.583,19.607],"ix":1},"s":{"a":0,"k":[100,100],"ix":3},"r":{"a":0,"k":0,"ix":6},"o":{"a":0,"k":100,"ix":7},"sk":{"a":0,"k":0,"ix":4},"sa":{"a":0,"k":0,"ix":5},"nm":"Transform"}],"nm":"R","np":2,"cix":2,"bm":0,"ix":1,"mn":"ADBE Vector Group","hd":false},{"ty":"gr","it":[{"ty":"gr","it":[{"ind":0,"ty":"sh","ix":1,"ks":{"a":0,"k":{"i":[[0.247,-2.09],[0.796,-2.452],[1.865,-0.302],[4.482,0.668],[-0.095,1.56],[-0.145,3.409],[0.027,2.089],[-1.86,0.282],[-4.243,-0.245],[-0.292,-3.708]],"o":[[-0.809,2.448],[-0.58,1.784],[-4.508,0.732],[-1.421,-0.212],[0.208,-3.402],[0.616,-2.075],[-0.024,-1.937],[4.201,-0.636],[3.668,0.211],[0.169,2.151]],"v":[[10.477,0.98],[8.054,8.325],[4.398,11.153],[-9.048,11.038],[-11.1,8.75],[-10.646,-1.47],[-10.414,-7.754],[-7.785,-10.952],[4.882,-11.64],[11.026,-5.312]],"c":true},"ix":2},"nm":"Path 1","mn":"ADBE Vector Shape - Group","hd":false},{"ty":"fl","c":{"a":0,"k":[0.141176470588,0.141176470588,0.141176470588,1],"ix":4},"o":{"a":0,"k":100,"ix":5},"r":1,"bm":0,"nm":"Fill 1","mn":"ADBE Vector Graphic - Fill","hd":false},{"ty":"tr","p":{"a":1,"k":[{"i":{"x":0.42,"y":1},"o":{"x":0.268,"y":0.876},"t":43,"s":[15.58,24.099],"to":[-0.083,0.958],"ti":[0,0]},{"i":{"x":0.306,"y":1},"o":{"x":0.477,"y":0},"t":61,"s":[15.08,29.849],"to":[0,0],"ti":[-0.083,0.958]},{"t":73,"s":[15.58,24.099]}],"ix":2},"a":{"a":0,"k":[0,0],"ix":1},"s":{"a":0,"k":[100,100],"ix":3},"r":{"a":0,"k":0,"ix":6},"o":{"a":0,"k":100,"ix":7},"sk":{"a":0,"k":0,"ix":4},"sa":{"a":0,"k":0,"ix":5},"nm":"Transform"}],"nm":"Group 2","np":2,"cix":2,"bm":0,"ix":1,"mn":"ADBE Vector Group","hd":false},{"ty":"gr","it":[{"ind":0,"ty":"sh","ix":1,"ks":{"a":0,"k":{"i":[[-2.89,-1.426],[1.259,-5.795],[6.813,-4.465],[5.976,0.057],[3.826,2.895],[0.368,0.99],[-2.489,7.72],[-1.79,1.17],[-1.089,1.465],[-6.553,-1.383]],"o":[[4.34,2.142],[-1.73,7.966],[-4.915,3.221],[-4.526,-0.042],[-0.816,-0.617],[-2.594,-6.992],[0.801,-2.485],[1.482,-0.969],[4.832,-6.501],[3.036,0.641]],"v":[[17.901,-14.189],[24.104,-2.849],[11.719,16.498],[-5.146,20.73],[-17.993,17.453],[-20.085,15.295],[-22.874,-6.351],[-18.329,-10.887],[-14.423,-14.286],[8.546,-17.123]],"c":true},"ix":2},"nm":"Path 1","mn":"ADBE Vector Shape - Group","hd":false},{"ty":"fl","c":{"a":0,"k":[1,1,1,1],"ix":4},"o":{"a":0,"k":100,"ix":5},"r":1,"bm":0,"nm":"Fill 1","mn":"ADBE Vector Graphic - Fill","hd":false},{"ty":"tr","p":{"a":0,"k":[25.612,22.01],"ix":2},"a":{"a":0,"k":[0,0],"ix":1},"s":{"a":0,"k":[100,100],"ix":3},"r":{"a":0,"k":0,"ix":6},"o":{"a":0,"k":100,"ix":7},"sk":{"a":0,"k":0,"ix":4},"sa":{"a":0,"k":0,"ix":5},"nm":"Transform"}],"nm":"Group 4","np":2,"cix":2,"bm":0,"ix":2,"mn":"ADBE Vector Group","hd":false},{"ty":"tr","p":{"a":0,"k":[25.873,23.044],"ix":2},"a":{"a":0,"k":[25.873,23.044],"ix":1},"s":{"a":0,"k":[100,100],"ix":3},"r":{"a":0,"k":0,"ix":6},"o":{"a":0,"k":100,"ix":7},"sk":{"a":0,"k":0,"ix":4},"sa":{"a":0,"k":0,"ix":5},"nm":"Transform"}],"nm":"L","np":2,"cix":2,"bm":0,"ix":2,"mn":"ADBE Vector Group","hd":false}],"ip":43,"op":120,"st":-43,"bm":0},{"ddd":0,"ind":6,"ty":4,"nm":"D 2","parent":2,"sr":1,"ks":{"o":{"a":0,"k":100,"ix":11},"r":{"a":0,"k":0,"ix":10},"p":{"a":0,"k":[24.237,43.872,0],"ix":2},"a":{"a":0,"k":[38.434,21.87,0],"ix":1},"s":{"a":0,"k":[100,100,100],"ix":6}},"ao":0,"shapes":[{"ty":"gr","it":[{"ind":0,"ty":"sh","ix":1,"ks":{"a":0,"k":{"i":[[1.463,0.014],[12.61,0.964],[3.564,1.019],[-0.47,1.416],[-1.563,3.331],[0,0],[-12.928,2.231],[-1.884,-8.072],[0.018,-7.044]],"o":[[-12.621,-0.121],[-3.576,-0.274],[-1.722,-0.493],[1.16,-3.499],[0.001,0],[4.799,-12.777],[8.003,-1.381],[1.932,6.768],[-0.007,2.275]],"v":[[23.869,18.375],[-13.991,17.75],[-24.725,16.882],[-26.155,14.335],[-21.94,4.146],[-21.939,4.146],[5.579,-17.574],[23.846,-4.391],[26.637,16.316]],"c":true},"ix":2},"nm":"Path 1","mn":"ADBE Vector Shape - Group","hd":false},{"ind":1,"ty":"sh","ix":2,"ks":{"a":0,"k":{"i":[[2.354,7.436],[7.686,1.503],[7.675,-1.985],[4.852,-13.295],[0.564,-4.426],[-2.851,0.094],[-14.353,0.457],[-8.832,0.702],[-0.04,2.397]],"o":[[-2.51,-7.929],[-7.662,-1.497],[-13.013,3.365],[-1.491,4.087],[-0.309,2.421],[14.348,-0.476],[8.826,-0.26],[2.512,-0.199],[0.13,-7.864]],"v":[[34.697,-5.728],[18.301,-20.053],[-5.176,-19.342],[-33.417,4.253],[-37.817,16.544],[-34.688,20.207],[8.319,21.092],[34.811,20.738],[37.996,17.281]],"c":true},"ix":2},"nm":"Path 2","mn":"ADBE Vector Shape - Group","hd":false},{"ty":"mm","mm":1,"nm":"Merge Paths 1","mn":"ADBE Vector Filter - Merge","hd":false},{"ty":"fl","c":{"a":0,"k":[0.141176470588,0.141176470588,0.141176470588,1],"ix":4},"o":{"a":0,"k":100,"ix":5},"r":1,"bm":0,"nm":"Fill 1","mn":"ADBE Vector Graphic - Fill","hd":false},{"ty":"tr","p":{"a":0,"k":[38.376,21.8],"ix":2},"a":{"a":0,"k":[0,0],"ix":1},"s":{"a":0,"k":[100,100],"ix":3},"r":{"a":0,"k":0,"ix":6},"o":{"a":0,"k":100,"ix":7},"sk":{"a":0,"k":0,"ix":4},"sa":{"a":0,"k":0,"ix":5},"nm":"Transform"}],"nm":"Group 1","np":4,"cix":2,"bm":0,"ix":1,"mn":"ADBE Vector Group","hd":false}],"ip":13,"op":43,"st":0,"bm":0},{"ddd":0,"ind":7,"ty":4,"nm":"XX 3","parent":2,"sr":1,"ks":{"o":{"a":0,"k":100,"ix":11},"r":{"a":0,"k":2.959,"ix":10},"p":{"a":0,"k":[30.379,1.487,0],"ix":2},"a":{"a":0,"k":[70.471,18.968,0],"ix":1},"s":{"a":0,"k":[100,100,100],"ix":6}},"ao":0,"shapes":[{"ty":"gr","it":[{"ind":0,"ty":"sh","ix":1,"ks":{"a":0,"k":{"i":[[1.143,0],[2.665,2.134],[0.318,0.207],[3.581,-7.478],[6.662,0.188],[-1.307,4.024],[-2.085,3.482],[1.526,0.845],[3.931,2.235],[-0.015,0.566],[-0.525,0.015],[-4.192,-4.005],[-1.776,3.118],[-1.666,3.09],[-1.495,0.018],[-2.458,-0.136],[1.151,-1.828],[3.124,-4.981],[-1.477,-0.735],[-4.166,-3.58],[0.329,-1.177],[1.094,-0.076]],"o":[[-3.235,0.752],[-0.296,-0.237],[-6.451,-4.193],[-2.837,5.926],[-4.376,-0.123],[1.293,-3.978],[0.994,-1.66],[-3.955,-2.191],[-0.402,-0.228],[0.019,-0.711],[4.831,-0.137],[2.669,2.55],[1.738,-3.051],[0.692,-1.285],[2.465,-0.03],[1.148,0.063],[-3.133,4.975],[-0.997,1.589],[4.823,2.402],[0.826,0.709],[-0.336,1.201],[-0.755,0.053]],"v":[[16.454,12.96],[7.723,9.937],[6.794,9.277],[-2.699,12.172],[-11.885,18.059],[-14.762,13.947],[-8.876,3.261],[-9.755,-0.049],[-21.555,-6.738],[-22.495,-7.674],[-21.311,-8.633],[-7.357,-5.984],[-2.671,-6.808],[2.529,-15.968],[5.564,-18.161],[12.958,-18.111],[14.094,-16.031],[5.023,-0.9],[5.829,2.128],[19.96,9.942],[22.182,12.194],[19.113,12.95]],"c":true},"ix":2},"nm":"Path 1","mn":"ADBE Vector Shape - Group","hd":false},{"ty":"fl","c":{"a":0,"k":[0.141176470588,0.141176470588,0.141176470588,1],"ix":4},"o":{"a":0,"k":100,"ix":5},"r":1,"bm":0,"nm":"Fill 1","mn":"ADBE Vector Graphic - Fill","hd":false},{"ty":"tr","p":{"a":0,"k":[22.76,18.497],"ix":2},"a":{"a":0,"k":[0,0],"ix":1},"s":{"a":0,"k":[100,100],"ix":3},"r":{"a":0,"k":0,"ix":6},"o":{"a":0,"k":100,"ix":7},"sk":{"a":0,"k":0,"ix":4},"sa":{"a":0,"k":0,"ix":5},"nm":"Transform"}],"nm":"Group 1","np":2,"cix":2,"bm":0,"ix":1,"mn":"ADBE Vector Group","hd":false},{"ty":"gr","it":[{"ind":0,"ty":"sh","ix":1,"ks":{"a":0,"k":{"i":[[-1.612,0.08],[-1.956,-3.905],[-4.268,4.922],[-4.117,-0.15],[0.756,-0.819],[3.709,-3.251],[-1.321,-1.55],[-2.35,-4.527],[1.639,-0.245],[2.654,0.231],[0.066,0.806],[0.96,3.155],[2.204,-2.149],[1.428,-1.826],[1.449,-0.11],[1.424,0.014],[0.356,1.11],[-0.721,0.549],[-3.835,2.625],[1.051,1.497],[4.34,3.605],[-0.558,0.074]],"o":[[4.657,-0.777],[2.982,5.954],[3.612,-4.166],[1.761,0.064],[-3.365,3.648],[-1.439,1.261],[3.366,3.951],[0.755,1.455],[-2.637,0.395],[-0.671,-0.059],[-0.276,-3.407],[-0.597,-1.962],[-1.612,1.572],[-1.151,1.471],[-1.415,0.107],[-0.947,-0.009],[-0.361,-1.126],[3.698,-2.821],[1.669,-1.141],[-3.077,-4.386],[-1.092,-0.907],[1.594,-0.213]],"v":[[-9.942,-17.972],[-0.861,-12.381],[6.803,-11.217],[18.874,-13.521],[18.902,-11.382],[7.743,-1.662],[7.354,1.921],[14.54,15.417],[12.926,18.354],[4.967,18.406],[3.49,17.321],[-0.096,8.179],[-4.169,7.089],[-9.329,11.519],[-13.583,12.476],[-17.854,12.462],[-20.274,11.465],[-18.859,9.231],[-7.669,0.899],[-6.861,-2.765],[-15.59,-16.265],[-14.771,-17.686]],"c":true},"ix":2},"nm":"Path 1","mn":"ADBE Vector Shape - Group","hd":false},{"ty":"fl","c":{"a":0,"k":[0.141176470588,0.141176470588,0.141176470588,1],"ix":4},"o":{"a":0,"k":100,"ix":5},"r":1,"bm":0,"nm":"Fill 1","mn":"ADBE Vector Graphic - Fill","hd":false},{"ty":"tr","p":{"a":0,"k":[120.813,19.022],"ix":2},"a":{"a":0,"k":[0,0],"ix":1},"s":{"a":0,"k":[100,100],"ix":3},"r":{"a":0,"k":0,"ix":6},"o":{"a":0,"k":100,"ix":7},"sk":{"a":0,"k":0,"ix":4},"sa":{"a":0,"k":0,"ix":5},"nm":"Transform"}],"nm":"Group 2","np":2,"cix":2,"bm":0,"ix":2,"mn":"ADBE Vector Group","hd":false}],"ip":13,"op":43,"st":0,"bm":0},{"ddd":0,"ind":8,"ty":4,"nm":"Smile 8","parent":2,"sr":1,"ks":{"o":{"a":0,"k":100,"ix":11},"r":{"a":0,"k":8.394,"ix":10},"p":{"a":0,"k":[35.181,58.888,0],"ix":2},"a":{"a":0,"k":[58.185,28.08,0],"ix":1},"s":{"a":0,"k":[100,100,100],"ix":6}},"ao":0,"shapes":[{"ty":"gr","it":[{"ind":0,"ty":"sh","ix":1,"ks":{"a":0,"k":{"i":[[0,0],[1.143,-1.406],[6.49,-3.526],[8.885,0.907],[1.043,-0.018],[5.503,1.405],[0.51,0.365],[3.164,1.453],[0.621,0.311],[3.027,7.2],[-2.867,1.347],[-10.96,2.688],[-11.765,1.246],[-8.159,0.787]],"o":[[-0.819,1.616],[-4.682,5.758],[-7.565,4.112],[-1.033,-0.105],[-5.812,0.099],[-0.599,-0.153],[-2.844,-2.038],[-0.605,-0.344],[-6.972,-3.49],[-1.214,-2.889],[10.277,-4.83],[11.495,-2.82],[8.153,-0.864],[0,0]],"v":[[43.999,-0.093],[41.046,4.432],[24.047,18.004],[-0.143,24.452],[-3.273,24.441],[-19.947,21.022],[-21.594,20.133],[-30.74,15.146],[-32.604,14.213],[-47.71,-1.753],[-45.697,-6.514],[-13.348,-16.302],[21.743,-22.065],[46.222,-24.424]],"c":true},"ix":2},"nm":"Path 1","mn":"ADBE Vector Shape - Group","hd":false},{"ind":1,"ty":"sh","ix":2,"ks":{"a":0,"k":{"i":[[-0.089,6.738],[1.764,0.119],[6.572,-0.538],[12.015,-1.801],[5.419,-1.497],[1.343,-0.305],[4.941,-1.865],[0,0],[1.469,-0.396],[5.677,-1.645],[-0.148,-0.641],[-6.885,-4.651],[-4.05,-2.839],[-6.677,-1.204],[-6.543,0.01],[-3.164,1.076],[-8.093,7.642],[-2.231,5.584]],"o":[[0.024,-1.817],[-6.641,-0.448],[-12.108,0.99],[-5.539,0.83],[-1.352,0.264],[-5.112,1.164],[0,0],[-1.541,0.15],[-5.719,1.539],[-0.683,0.198],[1.903,8.212],[4.106,2.774],[5.867,4.113],[6.424,1.159],[3.332,-0.005],[10.433,-3.549],[4.37,-4.127],[2.596,-6.499]],"v":[[57.657,-24.996],[55.21,-27.483],[35.428,-26.488],[-0.779,-22.366],[-17.273,-19.037],[-21.327,-18.239],[-36.609,-14.527],[-36.609,-14.527],[-40.997,-13.264],[-57.408,-6.768],[-57.869,-5.437],[-44.331,13.604],[-31.318,20.648],[-11.844,26.772],[7.761,27.128],[17.663,25.9],[45.869,9.749],[55.494,-4.993]],"c":true},"ix":2},"nm":"Path 2","mn":"ADBE Vector Shape - Group","hd":false},{"ty":"mm","mm":1,"nm":"Merge Paths 1","mn":"ADBE Vector Filter - Merge","hd":false},{"ty":"fl","c":{"a":0,"k":[0.141176470588,0.141176470588,0.141176470588,1],"ix":4},"o":{"a":0,"k":100,"ix":5},"r":1,"bm":0,"nm":"Fill 1","mn":"ADBE Vector Graphic - Fill","hd":false},{"ty":"tr","p":{"a":0,"k":[58.34,28.181],"ix":2},"a":{"a":0,"k":[0,0],"ix":1},"s":{"a":0,"k":[100,100],"ix":3},"r":{"a":0,"k":0,"ix":6},"o":{"a":0,"k":100,"ix":7},"sk":{"a":0,"k":0,"ix":4},"sa":{"a":0,"k":0,"ix":5},"nm":"Transform"}],"nm":"Group 1","np":4,"cix":2,"bm":0,"ix":1,"mn":"ADBE Vector Group","hd":false}],"ip":0,"op":13,"st":-43,"bm":0},{"ddd":0,"ind":9,"ty":4,"nm":"Eyes_R 3","parent":2,"sr":1,"ks":{"o":{"a":0,"k":100,"ix":11},"r":{"a":0,"k":0,"ix":10},"p":{"a":0,"k":[39.338,5.242,0],"ix":2},"a":{"a":0,"k":[65.014,21.585,0],"ix":1},"s":{"a":0,"k":[100,100,100],"ix":6}},"ao":0,"shapes":[{"ty":"gr","it":[{"ty":"gr","it":[{"ind":0,"ty":"sh","ix":1,"ks":{"a":0,"k":{"i":[[-0.682,0.847],[-0.083,0.287],[-0.224,1.719],[-1.046,0.155],[-4.852,-3.328],[-0.171,-1.337],[0.074,-3.402],[4.955,-0.332],[3.481,-0.066],[0.393,1.53],[0.021,3.197]],"o":[[0.083,-0.283],[0.295,-1.714],[0.158,-1.199],[5.332,-0.793],[1.114,0.764],[0.438,3.424],[-1.449,3.639],[-3.483,0.234],[-1.504,0.028],[-0.84,-3.262],[0.534,-0.866]],"v":[[-9.636,-2.618],[-9.387,-3.472],[-8.522,-8.608],[-6.608,-10.706],[8.867,-8.686],[10.645,-5.879],[10.597,4.34],[2.789,11.593],[-7.647,11.986],[-10.243,9.742],[-9.995,0.143]],"c":true},"ix":2},"nm":"Path 1","mn":"ADBE Vector Shape - Group","hd":false},{"ty":"fl","c":{"a":0,"k":[0.141176470588,0.141176470588,0.141176470588,1],"ix":4},"o":{"a":0,"k":100,"ix":5},"r":1,"bm":0,"nm":"Fill 1","mn":"ADBE Vector Graphic - Fill","hd":false},{"ty":"tr","p":{"a":0,"k":[94.341,17.205],"ix":2},"a":{"a":0,"k":[0,0],"ix":1},"s":{"a":0,"k":[100,100],"ix":3},"r":{"a":0,"k":0,"ix":6},"o":{"a":0,"k":100,"ix":7},"sk":{"a":0,"k":0,"ix":4},"sa":{"a":0,"k":0,"ix":5},"nm":"Transform"}],"nm":"Group 1","np":2,"cix":2,"bm":0,"ix":1,"mn":"ADBE Vector Group","hd":false},{"ty":"gr","it":[{"ind":0,"ty":"sh","ix":1,"ks":{"a":0,"k":{"i":[[-1.662,-1.997],[2.933,-5.513],[2.264,-3.012],[4.758,-0.112],[4.004,1.124],[3.043,1.641],[0.482,3.073],[0.314,1.248],[-2.396,5.289],[-1.999,0.769],[-5.406,-0.089],[-1.173,-0.395],[-1.191,-0.905]],"o":[[3.15,3.784],[-1.727,3.246],[-2.512,3.345],[-3.933,0.092],[-3.497,-0.981],[-2.877,-1.551],[-0.199,-1.272],[-1.517,-6.016],[0.905,-1.999],[5.089,-1.957],[1.238,0.02],[1.417,0.479],[2.146,1.628]],"v":[[18.198,-11.021],[19.945,2.791],[14.663,12.489],[5.072,18.927],[-6.621,18.328],[-15.969,13.863],[-20.626,6.776],[-21.36,2.981],[-18.415,-13.738],[-13.432,-17.495],[4.785,-19.232],[8.45,-18.742],[12.277,-16.439]],"c":true},"ix":2},"nm":"Path 1","mn":"ADBE Vector Shape - Group","hd":false},{"ty":"fl","c":{"a":0,"k":[1,1,1,1],"ix":4},"o":{"a":0,"k":100,"ix":5},"r":1,"bm":0,"nm":"Fill 1","mn":"ADBE Vector Graphic - Fill","hd":false},{"ty":"tr","p":{"a":0,"k":[106.767,19.702],"ix":2},"a":{"a":0,"k":[0,0],"ix":1},"s":{"a":0,"k":[100,100],"ix":3},"r":{"a":0,"k":0,"ix":6},"o":{"a":0,"k":100,"ix":7},"sk":{"a":0,"k":0,"ix":4},"sa":{"a":0,"k":0,"ix":5},"nm":"Transform"}],"nm":"Group 3","np":2,"cix":2,"bm":0,"ix":2,"mn":"ADBE Vector Group","hd":false},{"ty":"tr","p":{"a":0,"k":[106.583,19.607],"ix":2},"a":{"a":0,"k":[106.583,19.607],"ix":1},"s":{"a":0,"k":[100,100],"ix":3},"r":{"a":0,"k":0,"ix":6},"o":{"a":0,"k":100,"ix":7},"sk":{"a":0,"k":0,"ix":4},"sa":{"a":0,"k":0,"ix":5},"nm":"Transform"}],"nm":"R","np":2,"cix":2,"bm":0,"ix":1,"mn":"ADBE Vector Group","hd":false},{"ty":"gr","it":[{"ty":"gr","it":[{"ind":0,"ty":"sh","ix":1,"ks":{"a":0,"k":{"i":[[0.247,-2.09],[0.796,-2.452],[1.865,-0.302],[4.482,0.668],[-0.095,1.56],[-0.145,3.409],[0.027,2.089],[-1.86,0.282],[-4.243,-0.245],[-0.292,-3.708]],"o":[[-0.809,2.448],[-0.58,1.784],[-4.508,0.732],[-1.421,-0.212],[0.208,-3.402],[0.616,-2.075],[-0.024,-1.937],[4.201,-0.636],[3.668,0.211],[0.169,2.151]],"v":[[10.477,0.98],[8.054,8.325],[4.398,11.153],[-9.048,11.038],[-11.1,8.75],[-10.646,-1.47],[-10.414,-7.754],[-7.785,-10.952],[4.882,-11.64],[11.026,-5.312]],"c":true},"ix":2},"nm":"Path 1","mn":"ADBE Vector Shape - Group","hd":false},{"ty":"fl","c":{"a":0,"k":[0.141176470588,0.141176470588,0.141176470588,1],"ix":4},"o":{"a":0,"k":100,"ix":5},"r":1,"bm":0,"nm":"Fill 1","mn":"ADBE Vector Graphic - Fill","hd":false},{"ty":"tr","p":{"a":0,"k":[14.362,21.49],"ix":2},"a":{"a":0,"k":[0,0],"ix":1},"s":{"a":0,"k":[100,100],"ix":3},"r":{"a":0,"k":0,"ix":6},"o":{"a":0,"k":100,"ix":7},"sk":{"a":0,"k":0,"ix":4},"sa":{"a":0,"k":0,"ix":5},"nm":"Transform"}],"nm":"Group 2","np":2,"cix":2,"bm":0,"ix":1,"mn":"ADBE Vector Group","hd":false},{"ty":"gr","it":[{"ind":0,"ty":"sh","ix":1,"ks":{"a":0,"k":{"i":[[-2.89,-1.426],[1.259,-5.795],[6.813,-4.465],[5.976,0.057],[3.826,2.895],[0.368,0.99],[-2.489,7.72],[-1.79,1.17],[-1.089,1.465],[-6.553,-1.383]],"o":[[4.34,2.142],[-1.73,7.966],[-4.915,3.221],[-4.526,-0.042],[-0.816,-0.617],[-2.594,-6.992],[0.801,-2.485],[1.482,-0.969],[4.832,-6.501],[3.036,0.641]],"v":[[17.901,-14.189],[24.104,-2.849],[11.719,16.498],[-5.146,20.73],[-17.993,17.453],[-20.085,15.295],[-22.874,-6.351],[-18.329,-10.887],[-14.423,-14.286],[8.546,-17.123]],"c":true},"ix":2},"nm":"Path 1","mn":"ADBE Vector Shape - Group","hd":false},{"ty":"fl","c":{"a":0,"k":[1,1,1,1],"ix":4},"o":{"a":0,"k":100,"ix":5},"r":1,"bm":0,"nm":"Fill 1","mn":"ADBE Vector Graphic - Fill","hd":false},{"ty":"tr","p":{"a":0,"k":[25.612,22.01],"ix":2},"a":{"a":0,"k":[0,0],"ix":1},"s":{"a":0,"k":[100,100],"ix":3},"r":{"a":0,"k":0,"ix":6},"o":{"a":0,"k":100,"ix":7},"sk":{"a":0,"k":0,"ix":4},"sa":{"a":0,"k":0,"ix":5},"nm":"Transform"}],"nm":"Group 4","np":2,"cix":2,"bm":0,"ix":2,"mn":"ADBE Vector Group","hd":false},{"ty":"tr","p":{"a":0,"k":[25.873,23.044],"ix":2},"a":{"a":0,"k":[25.873,23.044],"ix":1},"s":{"a":0,"k":[100,100],"ix":3},"r":{"a":0,"k":0,"ix":6},"o":{"a":0,"k":100,"ix":7},"sk":{"a":0,"k":0,"ix":4},"sa":{"a":0,"k":0,"ix":5},"nm":"Transform"}],"nm":"L","np":2,"cix":2,"bm":0,"ix":2,"mn":"ADBE Vector Group","hd":false}],"ip":0,"op":13,"st":-86,"bm":0},{"ddd":0,"ind":10,"ty":3,"nm":"C_L","parent":22,"sr":1,"ks":{"o":{"a":0,"k":0,"ix":11},"r":{"a":0,"k":0,"ix":10},"p":{"a":1,"k":[{"i":{"x":0.446,"y":1},"o":{"x":0.578,"y":0},"t":0,"s":[-137.5,-49.826,0],"to":[0,0,0],"ti":[0,0,0]},{"i":{"x":0.42,"y":1},"o":{"x":0.604,"y":0},"t":29,"s":[-181.5,-62.826,0],"to":[0,0,0],"ti":[0,0,0]},{"i":{"x":0.306,"y":1},"o":{"x":0.477,"y":0},"t":61,"s":[-178.5,8.174,0],"to":[0,0,0],"ti":[0,0,0]},{"t":76,"s":[-181.5,-7.826,0]}],"ix":2},"a":{"a":0,"k":[50,50,0],"ix":1},"s":{"a":0,"k":[100,100,100],"ix":6}},"ao":0,"ip":0,"op":480,"st":0,"bm":0},{"ddd":0,"ind":11,"ty":4,"nm":"Smile 10","parent":10,"sr":1,"ks":{"o":{"a":0,"k":100,"ix":11},"r":{"a":0,"k":-6.628,"ix":10},"p":{"a":0,"k":[89.319,72.82,0],"ix":2},"a":{"a":0,"k":[58.185,28.08,0],"ix":1},"s":{"a":0,"k":[-100,100,100],"ix":6}},"ao":0,"shapes":[{"ty":"gr","it":[{"ind":0,"ty":"sh","ix":1,"ks":{"a":0,"k":{"i":[[0,0],[1.143,-1.406],[6.49,-3.526],[8.885,0.907],[1.043,-0.018],[5.503,1.405],[0.51,0.365],[3.164,1.453],[0.621,0.311],[3.027,7.2],[-2.867,1.347],[-10.96,2.688],[-11.765,1.246],[-8.159,0.787]],"o":[[-0.819,1.616],[-4.682,5.758],[-7.565,4.112],[-1.033,-0.105],[-5.812,0.099],[-0.599,-0.153],[-2.844,-2.038],[-0.605,-0.344],[-6.972,-3.49],[-1.214,-2.889],[10.277,-4.83],[11.495,-2.82],[8.153,-0.864],[0,0]],"v":[[43.999,-0.093],[41.046,4.432],[24.047,18.004],[-0.143,24.452],[-3.273,24.441],[-19.947,21.022],[-21.594,20.133],[-30.74,15.146],[-32.604,14.213],[-47.71,-1.753],[-45.697,-6.514],[-13.348,-16.302],[21.743,-22.065],[46.222,-24.424]],"c":true},"ix":2},"nm":"Path 1","mn":"ADBE Vector Shape - Group","hd":false},{"ind":1,"ty":"sh","ix":2,"ks":{"a":0,"k":{"i":[[-0.089,6.738],[1.764,0.119],[6.572,-0.538],[12.015,-1.801],[5.419,-1.497],[1.343,-0.305],[4.941,-1.865],[0,0],[1.469,-0.396],[5.677,-1.645],[-0.148,-0.641],[-6.885,-4.651],[-4.05,-2.839],[-6.677,-1.204],[-6.543,0.01],[-3.164,1.076],[-8.093,7.642],[-2.231,5.584]],"o":[[0.024,-1.817],[-6.641,-0.448],[-12.108,0.99],[-5.539,0.83],[-1.352,0.264],[-5.112,1.164],[0,0],[-1.541,0.15],[-5.719,1.539],[-0.683,0.198],[1.903,8.212],[4.106,2.774],[5.867,4.113],[6.424,1.159],[3.332,-0.005],[10.433,-3.549],[4.37,-4.127],[2.596,-6.499]],"v":[[57.657,-24.996],[55.21,-27.483],[35.428,-26.488],[-0.779,-22.366],[-17.273,-19.037],[-21.327,-18.239],[-36.609,-14.527],[-36.609,-14.527],[-40.997,-13.264],[-57.408,-6.768],[-57.869,-5.437],[-44.331,13.604],[-31.318,20.648],[-11.844,26.772],[7.761,27.128],[17.663,25.9],[45.869,9.749],[55.494,-4.993]],"c":true},"ix":2},"nm":"Path 2","mn":"ADBE Vector Shape - Group","hd":false},{"ty":"mm","mm":1,"nm":"Merge Paths 1","mn":"ADBE Vector Filter - Merge","hd":false},{"ty":"fl","c":{"a":0,"k":[0.141176470588,0.141176470588,0.141176470588,1],"ix":4},"o":{"a":0,"k":100,"ix":5},"r":1,"bm":0,"nm":"Fill 1","mn":"ADBE Vector Graphic - Fill","hd":false},{"ty":"tr","p":{"a":0,"k":[58.34,28.181],"ix":2},"a":{"a":0,"k":[0,0],"ix":1},"s":{"a":0,"k":[100,100],"ix":3},"r":{"a":0,"k":0,"ix":6},"o":{"a":0,"k":100,"ix":7},"sk":{"a":0,"k":0,"ix":4},"sa":{"a":0,"k":0,"ix":5},"nm":"Transform"}],"nm":"Group 1","np":4,"cix":2,"bm":0,"ix":1,"mn":"ADBE Vector Group","hd":false}],"ip":66,"op":120,"st":-30,"bm":0},{"ddd":0,"ind":12,"ty":4,"nm":"Eyes_L 2","parent":10,"sr":1,"ks":{"o":{"a":0,"k":100,"ix":11},"r":{"a":0,"k":0,"ix":10},"p":{"a":0,"k":[88.55,14.592,0],"ix":2},"a":{"a":0,"k":[65.014,21.585,0],"ix":1},"s":{"a":0,"k":[100,100,100],"ix":6}},"ao":0,"shapes":[{"ty":"gr","it":[{"ind":0,"ty":"sh","ix":1,"ks":{"a":0,"k":{"i":[[-0.682,0.847],[-0.083,0.287],[-0.224,1.719],[-1.046,0.155],[-4.852,-3.328],[-0.171,-1.337],[0.074,-3.402],[4.955,-0.332],[3.481,-0.066],[0.393,1.53],[0.021,3.197]],"o":[[0.083,-0.283],[0.295,-1.714],[0.158,-1.199],[5.332,-0.793],[1.114,0.764],[0.438,3.424],[-1.449,3.639],[-3.483,0.234],[-1.504,0.028],[-0.84,-3.262],[0.534,-0.866]],"v":[[-9.636,-2.618],[-9.387,-3.472],[-8.522,-8.608],[-6.608,-10.706],[8.867,-8.686],[10.645,-5.879],[10.597,4.34],[2.789,11.593],[-7.647,11.986],[-10.243,9.742],[-9.995,0.143]],"c":true},"ix":2},"nm":"Path 1","mn":"ADBE Vector Shape - Group","hd":false},{"ty":"fl","c":{"a":0,"k":[0.141176470588,0.141176470588,0.141176470588,1],"ix":4},"o":{"a":0,"k":100,"ix":5},"r":1,"bm":0,"nm":"Fill 1","mn":"ADBE Vector Graphic - Fill","hd":false},{"ty":"tr","p":{"a":1,"k":[{"i":{"x":0.306,"y":1},"o":{"x":0.477,"y":0},"t":61,"s":[116.892,24.785],"to":[0,-0.583],"ti":[0,0.583]},{"t":76,"s":[116.892,21.285]}],"ix":2},"a":{"a":0,"k":[0,0],"ix":1},"s":{"a":0,"k":[100,100],"ix":3},"r":{"a":0,"k":0,"ix":6},"o":{"a":0,"k":100,"ix":7},"sk":{"a":0,"k":0,"ix":4},"sa":{"a":0,"k":0,"ix":5},"nm":"Transform"}],"nm":"Group 1","np":2,"cix":2,"bm":0,"ix":1,"mn":"ADBE Vector Group","hd":false},{"ty":"gr","it":[{"ind":0,"ty":"sh","ix":1,"ks":{"a":0,"k":{"i":[[0.247,-2.09],[0.796,-2.452],[1.865,-0.302],[4.482,0.668],[-0.095,1.56],[-0.145,3.409],[0.027,2.089],[-1.86,0.282],[-4.243,-0.245],[-0.292,-3.708]],"o":[[-0.809,2.448],[-0.58,1.784],[-4.508,0.732],[-1.421,-0.212],[0.208,-3.402],[0.616,-2.075],[-0.024,-1.937],[4.201,-0.636],[3.668,0.211],[0.169,2.151]],"v":[[10.477,0.98],[8.054,8.325],[4.398,11.153],[-9.048,11.038],[-11.1,8.75],[-10.646,-1.47],[-10.414,-7.754],[-7.785,-10.952],[4.882,-11.64],[11.026,-5.312]],"c":true},"ix":2},"nm":"Path 1","mn":"ADBE Vector Shape - Group","hd":false},{"ty":"fl","c":{"a":0,"k":[0.141176470588,0.141176470588,0.141176470588,1],"ix":4},"o":{"a":0,"k":100,"ix":5},"r":1,"bm":0,"nm":"Fill 1","mn":"ADBE Vector Graphic - Fill","hd":false},{"ty":"tr","p":{"a":1,"k":[{"i":{"x":0.306,"y":1},"o":{"x":0.477,"y":0},"t":61,"s":[36.982,26.099],"to":[0,-0.583],"ti":[0,0.583]},{"t":76,"s":[36.982,22.599]}],"ix":2},"a":{"a":0,"k":[0,0],"ix":1},"s":{"a":0,"k":[100,100],"ix":3},"r":{"a":0,"k":0,"ix":6},"o":{"a":0,"k":100,"ix":7},"sk":{"a":0,"k":0,"ix":4},"sa":{"a":0,"k":0,"ix":5},"nm":"Transform"}],"nm":"Group 2","np":2,"cix":2,"bm":0,"ix":2,"mn":"ADBE Vector Group","hd":false},{"ty":"gr","it":[{"ind":0,"ty":"sh","ix":1,"ks":{"a":0,"k":{"i":[[-1.662,-1.997],[2.933,-5.513],[2.264,-3.012],[4.758,-0.112],[4.004,1.124],[3.043,1.641],[0.482,3.073],[0.314,1.248],[-2.396,5.289],[-1.999,0.769],[-5.406,-0.089],[-1.173,-0.395],[-1.191,-0.905]],"o":[[3.15,3.784],[-1.727,3.246],[-2.512,3.345],[-3.933,0.092],[-3.497,-0.981],[-2.877,-1.551],[-0.199,-1.272],[-1.517,-6.016],[0.905,-1.999],[5.089,-1.957],[1.238,0.02],[1.417,0.479],[2.146,1.628]],"v":[[18.198,-11.022],[19.945,2.79],[14.663,12.488],[5.072,18.927],[-6.621,18.328],[-15.969,13.862],[-20.626,6.776],[-21.36,2.98],[-18.415,-13.737],[-13.432,-17.495],[4.785,-19.233],[8.45,-18.742],[12.277,-16.44]],"c":true},"ix":2},"nm":"Path 1","mn":"ADBE Vector Shape - Group","hd":false},{"ty":"fl","c":{"a":0,"k":[1,1,1,1],"ix":4},"o":{"a":0,"k":100,"ix":5},"r":1,"bm":0,"nm":"Fill 1","mn":"ADBE Vector Graphic - Fill","hd":false},{"ty":"tr","p":{"a":0,"k":[106.767,19.702],"ix":2},"a":{"a":0,"k":[0,0],"ix":1},"s":{"a":0,"k":[100,100],"ix":3},"r":{"a":0,"k":0,"ix":6},"o":{"a":0,"k":100,"ix":7},"sk":{"a":0,"k":0,"ix":4},"sa":{"a":0,"k":0,"ix":5},"nm":"Transform"}],"nm":"Group 3","np":2,"cix":2,"bm":0,"ix":3,"mn":"ADBE Vector Group","hd":false},{"ty":"gr","it":[{"ind":0,"ty":"sh","ix":1,"ks":{"a":0,"k":{"i":[[-2.89,-1.426],[1.259,-5.795],[6.813,-4.465],[5.976,0.057],[3.826,2.896],[0.368,0.99],[-2.489,7.72],[-1.79,1.17],[-1.089,1.465],[-6.553,-1.383]],"o":[[4.34,2.142],[-1.73,7.966],[-4.915,3.221],[-4.526,-0.042],[-0.816,-0.616],[-2.594,-6.992],[0.801,-2.485],[1.482,-0.969],[4.832,-6.501],[3.036,0.641]],"v":[[17.9,-14.189],[24.104,-2.849],[11.718,16.498],[-5.146,20.73],[-17.993,17.452],[-20.085,15.295],[-22.874,-6.351],[-18.329,-10.887],[-14.423,-14.286],[8.546,-17.123]],"c":true},"ix":2},"nm":"Path 1","mn":"ADBE Vector Shape - Group","hd":false},{"ty":"fl","c":{"a":0,"k":[1,1,1,1],"ix":4},"o":{"a":0,"k":100,"ix":5},"r":1,"bm":0,"nm":"Fill 1","mn":"ADBE Vector Graphic - Fill","hd":false},{"ty":"tr","p":{"a":0,"k":[25.612,22.01],"ix":2},"a":{"a":0,"k":[0,0],"ix":1},"s":{"a":0,"k":[100,100],"ix":3},"r":{"a":0,"k":0,"ix":6},"o":{"a":0,"k":100,"ix":7},"sk":{"a":0,"k":0,"ix":4},"sa":{"a":0,"k":0,"ix":5},"nm":"Transform"}],"nm":"Group 4","np":2,"cix":2,"bm":0,"ix":4,"mn":"ADBE Vector Group","hd":false}],"ip":66,"op":120,"st":66,"bm":0},{"ddd":0,"ind":13,"ty":4,"nm":"O 2","parent":10,"sr":1,"ks":{"o":{"a":0,"k":100,"ix":11},"r":{"a":0,"k":0,"ix":10},"p":{"a":0,"k":[48.344,81.719,0],"ix":2},"a":{"a":0,"k":[37.695,35.49,0],"ix":1},"s":{"a":0,"k":[100,100,100],"ix":6}},"ao":0,"shapes":[{"ty":"gr","it":[{"ind":0,"ty":"sh","ix":1,"ks":{"a":0,"k":{"i":[[1.138,-9.956],[2.103,-4.382],[11.323,-4.123],[3.685,2.051],[1.463,3.591],[-0.649,6.296],[-4.727,7.554],[-6.366,0.851],[-6.053,-3.513]],"o":[[-0.541,4.734],[-4.071,11.639],[-4.306,1.568],[-3.309,-1.842],[-2.313,-5.682],[0.113,-8.859],[3.261,-5.211],[6.507,-0.87],[9.351,5.424]],"v":[[25.542,-6.103],[21.869,7.747],[-1.839,30.879],[-13.917,28.514],[-21.475,20.355],[-25.014,2.551],[-18.652,-22.484],[-4.356,-32.995],[14.748,-29.884]],"c":true},"ix":2},"nm":"Path 1","mn":"ADBE Vector Shape - Group","hd":false},{"ind":1,"ty":"sh","ix":2,"ks":{"a":0,"k":{"i":[[11.558,2.246],[4.683,-0.205],[1.884,-0.027],[5.528,-8.229],[1.429,-4.852],[-3.138,-9.115],[-7.315,-2.382],[-3.162,-0.402],[-9.916,14.328],[-0.261,9.388]],"o":[[-5.358,-1.041],[-2.672,0],[-9.525,0.134],[-2.971,4.423],[-2.728,9.265],[2.512,7.3],[3.056,0.994],[17.11,2.174],[5.227,-7.553],[0.384,-13.796]],"v":[[15.452,-34.745],[-0.058,-35.836],[-6.499,-35.832],[-29.206,-24.072],[-34.477,-9.913],[-33.8,17.553],[-19.166,32.049],[-9.788,33.867],[29.279,15.654],[36.822,-10.315]],"c":true},"ix":2},"nm":"Path 2","mn":"ADBE Vector Shape - Group","hd":false},{"ty":"mm","mm":1,"nm":"Merge Paths 1","mn":"ADBE Vector Filter - Merge","hd":false},{"ty":"fl","c":{"a":0,"k":[0.141176470588,0.141176470588,0.141176470588,1],"ix":4},"o":{"a":0,"k":100,"ix":5},"r":1,"bm":0,"nm":"Fill 1","mn":"ADBE Vector Graphic - Fill","hd":false},{"ty":"tr","p":{"a":0,"k":[37.455,36.292],"ix":2},"a":{"a":0,"k":[0,0],"ix":1},"s":{"a":0,"k":[100,100],"ix":3},"r":{"a":0,"k":0,"ix":6},"o":{"a":0,"k":100,"ix":7},"sk":{"a":0,"k":0,"ix":4},"sa":{"a":0,"k":0,"ix":5},"nm":"Transform"}],"nm":"Group 1","np":4,"cix":2,"bm":0,"ix":1,"mn":"ADBE Vector Group","hd":false}],"ip":43,"op":66,"st":43,"bm":0},{"ddd":0,"ind":14,"ty":4,"nm":"Smile 7","parent":10,"sr":1,"ks":{"o":{"a":0,"k":100,"ix":11},"r":{"a":0,"k":-6.628,"ix":10},"p":{"a":0,"k":[46.319,76.82,0],"ix":2},"a":{"a":0,"k":[58.185,28.08,0],"ix":1},"s":{"a":0,"k":[-100,100,100],"ix":6}},"ao":0,"shapes":[{"ty":"gr","it":[{"ind":0,"ty":"sh","ix":1,"ks":{"a":0,"k":{"i":[[0,0],[1.143,-1.406],[6.49,-3.526],[8.885,0.907],[1.043,-0.018],[5.503,1.405],[0.51,0.365],[3.164,1.453],[0.621,0.311],[3.027,7.2],[-2.867,1.347],[-10.96,2.688],[-11.765,1.246],[-8.159,0.787]],"o":[[-0.819,1.616],[-4.682,5.758],[-7.565,4.112],[-1.033,-0.105],[-5.812,0.099],[-0.599,-0.153],[-2.844,-2.038],[-0.605,-0.344],[-6.972,-3.49],[-1.214,-2.889],[10.277,-4.83],[11.495,-2.82],[8.153,-0.864],[0,0]],"v":[[43.999,-0.093],[41.046,4.432],[24.047,18.004],[-0.143,24.452],[-3.273,24.441],[-19.947,21.022],[-21.594,20.133],[-30.74,15.146],[-32.604,14.213],[-47.71,-1.753],[-45.697,-6.514],[-13.348,-16.302],[21.743,-22.065],[46.222,-24.424]],"c":true},"ix":2},"nm":"Path 1","mn":"ADBE Vector Shape - Group","hd":false},{"ind":1,"ty":"sh","ix":2,"ks":{"a":0,"k":{"i":[[-0.089,6.738],[1.764,0.119],[6.572,-0.538],[12.015,-1.801],[5.419,-1.497],[1.343,-0.305],[4.941,-1.865],[0,0],[1.469,-0.396],[5.677,-1.645],[-0.148,-0.641],[-6.885,-4.651],[-4.05,-2.839],[-6.677,-1.204],[-6.543,0.01],[-3.164,1.076],[-8.093,7.642],[-2.231,5.584]],"o":[[0.024,-1.817],[-6.641,-0.448],[-12.108,0.99],[-5.539,0.83],[-1.352,0.264],[-5.112,1.164],[0,0],[-1.541,0.15],[-5.719,1.539],[-0.683,0.198],[1.903,8.212],[4.106,2.774],[5.867,4.113],[6.424,1.159],[3.332,-0.005],[10.433,-3.549],[4.37,-4.127],[2.596,-6.499]],"v":[[57.657,-24.996],[55.21,-27.483],[35.428,-26.488],[-0.779,-22.366],[-17.273,-19.037],[-21.327,-18.239],[-36.609,-14.527],[-36.609,-14.527],[-40.997,-13.264],[-57.408,-6.768],[-57.869,-5.437],[-44.331,13.604],[-31.318,20.648],[-11.844,26.772],[7.761,27.128],[17.663,25.9],[45.869,9.749],[55.494,-4.993]],"c":true},"ix":2},"nm":"Path 2","mn":"ADBE Vector Shape - Group","hd":false},{"ty":"mm","mm":1,"nm":"Merge Paths 1","mn":"ADBE Vector Filter - Merge","hd":false},{"ty":"fl","c":{"a":0,"k":[0.141176470588,0.141176470588,0.141176470588,1],"ix":4},"o":{"a":0,"k":100,"ix":5},"r":1,"bm":0,"nm":"Fill 1","mn":"ADBE Vector Graphic - Fill","hd":false},{"ty":"tr","p":{"a":0,"k":[58.34,28.181],"ix":2},"a":{"a":0,"k":[0,0],"ix":1},"s":{"a":0,"k":[100,100],"ix":3},"r":{"a":0,"k":0,"ix":6},"o":{"a":0,"k":100,"ix":7},"sk":{"a":0,"k":0,"ix":4},"sa":{"a":0,"k":0,"ix":5},"nm":"Transform"}],"nm":"Group 1","np":4,"cix":2,"bm":0,"ix":1,"mn":"ADBE Vector Group","hd":false}],"ip":13,"op":43,"st":-30,"bm":0},{"ddd":0,"ind":15,"ty":4,"nm":"O","parent":10,"sr":1,"ks":{"o":{"a":0,"k":100,"ix":11},"r":{"a":0,"k":0,"ix":10},"p":{"a":0,"k":[46.858,87.806,0],"ix":2},"a":{"a":0,"k":[37.695,35.49,0],"ix":1},"s":{"a":0,"k":[100,100,100],"ix":6}},"ao":0,"shapes":[{"ty":"gr","it":[{"ind":0,"ty":"sh","ix":1,"ks":{"a":0,"k":{"i":[[1.138,-9.956],[2.103,-4.382],[11.323,-4.123],[3.685,2.051],[1.463,3.591],[-0.649,6.296],[-4.727,7.554],[-6.366,0.851],[-6.053,-3.513]],"o":[[-0.541,4.734],[-4.071,11.639],[-4.306,1.568],[-3.309,-1.842],[-2.313,-5.682],[0.113,-8.859],[3.261,-5.211],[6.507,-0.87],[9.351,5.424]],"v":[[25.542,-6.103],[21.869,7.747],[-1.839,30.879],[-13.917,28.514],[-21.475,20.355],[-25.014,2.551],[-18.652,-22.484],[-4.356,-32.995],[14.748,-29.884]],"c":true},"ix":2},"nm":"Path 1","mn":"ADBE Vector Shape - Group","hd":false},{"ind":1,"ty":"sh","ix":2,"ks":{"a":0,"k":{"i":[[11.558,2.246],[4.683,-0.205],[1.884,-0.027],[5.528,-8.229],[1.429,-4.852],[-3.138,-9.115],[-7.315,-2.382],[-3.162,-0.402],[-9.916,14.328],[-0.261,9.388]],"o":[[-5.358,-1.041],[-2.672,0],[-9.525,0.134],[-2.971,4.423],[-2.728,9.265],[2.512,7.3],[3.056,0.994],[17.11,2.174],[5.227,-7.553],[0.384,-13.796]],"v":[[15.452,-34.745],[-0.058,-35.836],[-6.499,-35.832],[-29.206,-24.072],[-34.477,-9.913],[-33.8,17.553],[-19.166,32.049],[-9.788,33.867],[29.279,15.654],[36.822,-10.315]],"c":true},"ix":2},"nm":"Path 2","mn":"ADBE Vector Shape - Group","hd":false},{"ty":"mm","mm":1,"nm":"Merge Paths 1","mn":"ADBE Vector Filter - Merge","hd":false},{"ty":"fl","c":{"a":0,"k":[0.141176470588,0.141176470588,0.141176470588,1],"ix":4},"o":{"a":0,"k":100,"ix":5},"r":1,"bm":0,"nm":"Fill 1","mn":"ADBE Vector Graphic - Fill","hd":false},{"ty":"tr","p":{"a":0,"k":[37.455,36.292],"ix":2},"a":{"a":0,"k":[0,0],"ix":1},"s":{"a":0,"k":[100,100],"ix":3},"r":{"a":0,"k":0,"ix":6},"o":{"a":0,"k":100,"ix":7},"sk":{"a":0,"k":0,"ix":4},"sa":{"a":0,"k":0,"ix":5},"nm":"Transform"}],"nm":"Group 1","np":4,"cix":2,"bm":0,"ix":1,"mn":"ADBE Vector Group","hd":false}],"ip":0,"op":13,"st":0,"bm":0},{"ddd":0,"ind":16,"ty":4,"nm":"Eyes_L 3","parent":10,"sr":1,"ks":{"o":{"a":0,"k":100,"ix":11},"r":{"a":0,"k":0,"ix":10},"p":{"a":0,"k":[49.55,19.592,0],"ix":2},"a":{"a":0,"k":[65.014,21.585,0],"ix":1},"s":{"a":0,"k":[100,100,100],"ix":6}},"ao":0,"shapes":[{"ty":"gr","it":[{"ind":0,"ty":"sh","ix":1,"ks":{"a":0,"k":{"i":[[-0.682,0.847],[-0.083,0.287],[-0.224,1.719],[-1.046,0.155],[-4.852,-3.328],[-0.171,-1.337],[0.074,-3.402],[4.955,-0.332],[3.481,-0.066],[0.393,1.53],[0.021,3.197]],"o":[[0.083,-0.283],[0.295,-1.714],[0.158,-1.199],[5.332,-0.793],[1.114,0.764],[0.438,3.424],[-1.449,3.639],[-3.483,0.234],[-1.504,0.028],[-0.84,-3.262],[0.534,-0.866]],"v":[[-9.636,-2.618],[-9.387,-3.472],[-8.522,-8.608],[-6.608,-10.706],[8.867,-8.686],[10.645,-5.879],[10.597,4.34],[2.789,11.593],[-7.647,11.986],[-10.243,9.742],[-9.995,0.143]],"c":true},"ix":2},"nm":"Path 1","mn":"ADBE Vector Shape - Group","hd":false},{"ty":"fl","c":{"a":0,"k":[0.141176470588,0.141176470588,0.141176470588,1],"ix":4},"o":{"a":0,"k":100,"ix":5},"r":1,"bm":0,"nm":"Fill 1","mn":"ADBE Vector Graphic - Fill","hd":false},{"ty":"tr","p":{"a":1,"k":[{"i":{"x":0.446,"y":1},"o":{"x":0.578,"y":0},"t":0,"s":[116.892,24.785],"to":[0,-0.333],"ti":[0,0.333]},{"i":{"x":0.446,"y":0.446},"o":{"x":0.604,"y":0.604},"t":29,"s":[116.892,22.785],"to":[0,0],"ti":[0,0]},{"i":{"x":0.446,"y":1},"o":{"x":0.167,"y":0},"t":43,"s":[116.892,22.785],"to":[0,-0.667],"ti":[0,0.667]},{"t":52,"s":[116.892,18.785]}],"ix":2},"a":{"a":0,"k":[0,0],"ix":1},"s":{"a":0,"k":[100,100],"ix":3},"r":{"a":0,"k":0,"ix":6},"o":{"a":0,"k":100,"ix":7},"sk":{"a":0,"k":0,"ix":4},"sa":{"a":0,"k":0,"ix":5},"nm":"Transform"}],"nm":"Group 1","np":2,"cix":2,"bm":0,"ix":1,"mn":"ADBE Vector Group","hd":false},{"ty":"gr","it":[{"ind":0,"ty":"sh","ix":1,"ks":{"a":0,"k":{"i":[[0.247,-2.09],[0.796,-2.452],[1.865,-0.302],[4.482,0.668],[-0.095,1.56],[-0.145,3.409],[0.027,2.089],[-1.86,0.282],[-4.243,-0.245],[-0.292,-3.708]],"o":[[-0.809,2.448],[-0.58,1.784],[-4.508,0.732],[-1.421,-0.212],[0.208,-3.402],[0.616,-2.075],[-0.024,-1.937],[4.201,-0.636],[3.668,0.211],[0.169,2.151]],"v":[[10.477,0.98],[8.054,8.325],[4.398,11.153],[-9.048,11.038],[-11.1,8.75],[-10.646,-1.47],[-10.414,-7.754],[-7.785,-10.952],[4.882,-11.64],[11.026,-5.312]],"c":true},"ix":2},"nm":"Path 1","mn":"ADBE Vector Shape - Group","hd":false},{"ty":"fl","c":{"a":0,"k":[0.141176470588,0.141176470588,0.141176470588,1],"ix":4},"o":{"a":0,"k":100,"ix":5},"r":1,"bm":0,"nm":"Fill 1","mn":"ADBE Vector Graphic - Fill","hd":false},{"ty":"tr","p":{"a":1,"k":[{"i":{"x":0.446,"y":1},"o":{"x":0.578,"y":0},"t":0,"s":[36.982,26.099],"to":[0,-0.333],"ti":[0,0.333]},{"i":{"x":0.446,"y":0.446},"o":{"x":0.604,"y":0.604},"t":29,"s":[36.982,24.099],"to":[0,0],"ti":[0,0]},{"i":{"x":0.446,"y":1},"o":{"x":0.167,"y":0},"t":43,"s":[36.982,24.099],"to":[0,-0.667],"ti":[0,0.667]},{"t":52,"s":[36.982,20.099]}],"ix":2},"a":{"a":0,"k":[0,0],"ix":1},"s":{"a":0,"k":[100,100],"ix":3},"r":{"a":0,"k":0,"ix":6},"o":{"a":0,"k":100,"ix":7},"sk":{"a":0,"k":0,"ix":4},"sa":{"a":0,"k":0,"ix":5},"nm":"Transform"}],"nm":"Group 2","np":2,"cix":2,"bm":0,"ix":2,"mn":"ADBE Vector Group","hd":false},{"ty":"gr","it":[{"ind":0,"ty":"sh","ix":1,"ks":{"a":0,"k":{"i":[[-1.662,-1.997],[2.933,-5.513],[2.264,-3.012],[4.758,-0.112],[4.004,1.124],[3.043,1.641],[0.482,3.073],[0.314,1.248],[-2.396,5.289],[-1.999,0.769],[-5.406,-0.089],[-1.173,-0.395],[-1.191,-0.905]],"o":[[3.15,3.784],[-1.727,3.246],[-2.512,3.345],[-3.933,0.092],[-3.497,-0.981],[-2.877,-1.551],[-0.199,-1.272],[-1.517,-6.016],[0.905,-1.999],[5.089,-1.957],[1.238,0.02],[1.417,0.479],[2.146,1.628]],"v":[[18.198,-11.022],[19.945,2.79],[14.663,12.488],[5.072,18.927],[-6.621,18.328],[-15.969,13.862],[-20.626,6.776],[-21.36,2.98],[-18.415,-13.737],[-13.432,-17.495],[4.785,-19.233],[8.45,-18.742],[12.277,-16.44]],"c":true},"ix":2},"nm":"Path 1","mn":"ADBE Vector Shape - Group","hd":false},{"ty":"fl","c":{"a":0,"k":[1,1,1,1],"ix":4},"o":{"a":0,"k":100,"ix":5},"r":1,"bm":0,"nm":"Fill 1","mn":"ADBE Vector Graphic - Fill","hd":false},{"ty":"tr","p":{"a":0,"k":[106.767,19.702],"ix":2},"a":{"a":0,"k":[0,0],"ix":1},"s":{"a":0,"k":[100,100],"ix":3},"r":{"a":0,"k":0,"ix":6},"o":{"a":0,"k":100,"ix":7},"sk":{"a":0,"k":0,"ix":4},"sa":{"a":0,"k":0,"ix":5},"nm":"Transform"}],"nm":"Group 3","np":2,"cix":2,"bm":0,"ix":3,"mn":"ADBE Vector Group","hd":false},{"ty":"gr","it":[{"ind":0,"ty":"sh","ix":1,"ks":{"a":0,"k":{"i":[[-2.89,-1.426],[1.259,-5.795],[6.813,-4.465],[5.976,0.057],[3.826,2.896],[0.368,0.99],[-2.489,7.72],[-1.79,1.17],[-1.089,1.465],[-6.553,-1.383]],"o":[[4.34,2.142],[-1.73,7.966],[-4.915,3.221],[-4.526,-0.042],[-0.816,-0.616],[-2.594,-6.992],[0.801,-2.485],[1.482,-0.969],[4.832,-6.501],[3.036,0.641]],"v":[[17.9,-14.189],[24.104,-2.849],[11.718,16.498],[-5.146,20.73],[-17.993,17.452],[-20.085,15.295],[-22.874,-6.351],[-18.329,-10.887],[-14.423,-14.286],[8.546,-17.123]],"c":true},"ix":2},"nm":"Path 1","mn":"ADBE Vector Shape - Group","hd":false},{"ty":"fl","c":{"a":0,"k":[1,1,1,1],"ix":4},"o":{"a":0,"k":100,"ix":5},"r":1,"bm":0,"nm":"Fill 1","mn":"ADBE Vector Graphic - Fill","hd":false},{"ty":"tr","p":{"a":0,"k":[25.612,22.01],"ix":2},"a":{"a":0,"k":[0,0],"ix":1},"s":{"a":0,"k":[100,100],"ix":3},"r":{"a":0,"k":0,"ix":6},"o":{"a":0,"k":100,"ix":7},"sk":{"a":0,"k":0,"ix":4},"sa":{"a":0,"k":0,"ix":5},"nm":"Transform"}],"nm":"Group 4","np":2,"cix":2,"bm":0,"ix":4,"mn":"ADBE Vector Group","hd":false}],"ip":0,"op":66,"st":0,"bm":0},{"ddd":0,"ind":18,"ty":4,"nm":"Side_03","td":1,"sr":1,"ks":{"o":{"a":0,"k":100,"ix":11},"r":{"a":0,"k":0,"ix":10},"p":{"a":0,"k":[564.5,200,0],"ix":2},"a":{"a":0,"k":[0,0,0],"ix":1},"s":{"a":0,"k":[100,100,100],"ix":6}},"ao":0,"shapes":[{"ty":"gr","it":[{"ty":"rc","d":1,"s":{"a":0,"k":[1004,325],"ix":2},"p":{"a":0,"k":[0,0],"ix":3},"r":{"a":0,"k":25,"ix":4},"nm":"Rectangle Path 1","mn":"ADBE Vector Shape - Rect","hd":false},{"ty":"st","c":{"a":0,"k":[1,1,1,1],"ix":3},"o":{"a":0,"k":100,"ix":4},"w":{"a":0,"k":0,"ix":5},"lc":1,"lj":1,"ml":4,"bm":0,"nm":"Stroke 1","mn":"ADBE Vector Graphic - Stroke","hd":false},{"ty":"fl","c":{"a":0,"k":[0.529411764706,0.298039215686,0.243137254902,1],"ix":4},"o":{"a":0,"k":100,"ix":5},"r":1,"bm":0,"nm":"Fill 1","mn":"ADBE Vector Graphic - Fill","hd":false},{"ty":"tr","p":{"a":0,"k":[-2.5,0],"ix":2},"a":{"a":0,"k":[0,0],"ix":1},"s":{"a":0,"k":[100,100],"ix":3},"r":{"a":0,"k":0,"ix":6},"o":{"a":0,"k":100,"ix":7},"sk":{"a":0,"k":0,"ix":4},"sa":{"a":0,"k":0,"ix":5},"nm":"Transform"}],"nm":"Rectangle 1","np":3,"cix":2,"bm":0,"ix":1,"mn":"ADBE Vector Group","hd":false}],"ip":0,"op":480,"st":0,"bm":0},{"ddd":0,"ind":19,"ty":4,"nm":"WaveLine","tt":1,"sr":1,"ks":{"o":{"a":0,"k":100,"ix":11},"r":{"a":0,"k":0,"ix":10},"p":{"a":1,"k":[{"i":{"x":0.446,"y":1},"o":{"x":0.578,"y":0},"t":0,"s":[296.5,200,0],"to":[21.175,0,0],"ti":[17.523,0,0]},{"i":{"x":0.451,"y":1},"o":{"x":0.604,"y":0},"t":29,"s":[993.816,200,0],"to":[-15.871,0,0],"ti":[-40.438,0,0]},{"i":{"x":0.306,"y":1},"o":{"x":0.477,"y":0},"t":61,"s":[289.742,200,0],"to":[27.545,0,0],"ti":[3.667,-0.333,0]},{"t":76,"s":[659,200,0]}],"ix":2},"a":{"a":0,"k":[0,0,0],"ix":1},"s":{"a":0,"k":[100,100,100],"ix":6}},"ao":0,"shapes":[{"ty":"gr","it":[{"ty":"rc","d":1,"s":{"a":0,"k":[1260,882],"ix":2},"p":{"a":0,"k":[0,0],"ix":3},"r":{"a":0,"k":0,"ix":4},"nm":"Rectangle Path 1","mn":"ADBE Vector Shape - Rect","hd":false},{"ty":"st","c":{"a":0,"k":[0.2,0.2,0.2,1],"ix":3},"o":{"a":0,"k":100,"ix":4},"w":{"a":0,"k":5,"ix":5},"lc":1,"lj":1,"ml":4,"bm":0,"nm":"Stroke 1","mn":"ADBE Vector Graphic - Stroke","hd":false},{"ty":"tr","p":{"a":0,"k":[-626.5,-5],"ix":2},"a":{"a":0,"k":[0,0],"ix":1},"s":{"a":0,"k":[100,100],"ix":3},"r":{"a":0,"k":0,"ix":6},"o":{"a":0,"k":100,"ix":7},"sk":{"a":0,"k":0,"ix":4},"sa":{"a":0,"k":0,"ix":5},"nm":"Transform"}],"nm":"Rectangle 1","np":3,"cix":2,"bm":0,"ix":1,"mn":"ADBE Vector Group","hd":false}],"ip":0,"op":480,"st":0,"bm":0},{"ddd":0,"ind":20,"ty":4,"nm":"Wave 2","td":1,"sr":1,"ks":{"o":{"a":0,"k":50,"ix":11},"r":{"a":0,"k":0,"ix":10},"p":{"a":1,"k":[{"i":{"x":0.446,"y":1},"o":{"x":0.578,"y":0},"t":0,"s":[301,195,0],"to":[21.175,0,0],"ti":[17.523,0,0]},{"i":{"x":0.451,"y":1},"o":{"x":0.604,"y":0},"t":29,"s":[998.316,195,0],"to":[-15.871,0,0],"ti":[-40.438,0,0]},{"i":{"x":0.306,"y":1},"o":{"x":0.477,"y":0},"t":61,"s":[294.242,195,0],"to":[27.545,0,0],"ti":[3.667,-0.333,0]},{"t":76,"s":[663.5,195,0]}],"ix":2},"a":{"a":0,"k":[-1259.5,-5,0],"ix":1},"s":{"a":0,"k":[63,63,100],"ix":6}},"ao":0,"shapes":[{"ty":"gr","it":[{"ty":"rc","d":1,"s":{"a":0,"k":[71,882],"ix":2},"p":{"a":0,"k":[0,0],"ix":3},"r":{"a":0,"k":0,"ix":4},"nm":"Rectangle Path 1","mn":"ADBE Vector Shape - Rect","hd":false},{"ty":"st","c":{"a":0,"k":[0.2,0.2,0.2,1],"ix":3},"o":{"a":0,"k":100,"ix":4},"w":{"a":0,"k":0,"ix":5},"lc":1,"lj":1,"ml":4,"bm":0,"nm":"Stroke 1","mn":"ADBE Vector Graphic - Stroke","hd":false},{"ty":"fl","c":{"a":0,"k":[0,0,0,1],"ix":4},"o":{"a":0,"k":100,"ix":5},"r":1,"bm":0,"nm":"Fill 1","mn":"ADBE Vector Graphic - Fill","hd":false},{"ty":"tr","p":{"a":0,"k":[-1259.5,-5],"ix":2},"a":{"a":0,"k":[0,0],"ix":1},"s":{"a":0,"k":[100,100],"ix":3},"r":{"a":0,"k":0,"ix":6},"o":{"a":0,"k":100,"ix":7},"sk":{"a":0,"k":0,"ix":4},"sa":{"a":0,"k":0,"ix":5},"nm":"Transform"}],"nm":"Rectangle 1","np":3,"cix":2,"bm":0,"ix":1,"mn":"ADBE Vector Group","hd":false}],"ip":0,"op":480,"st":0,"bm":0},{"ddd":0,"ind":21,"ty":4,"nm":"Side_04","tt":1,"sr":1,"ks":{"o":{"a":0,"k":100,"ix":11},"r":{"a":0,"k":0,"ix":10},"p":{"a":0,"k":[564.5,200,0],"ix":2},"a":{"a":0,"k":[0,0,0],"ix":1},"s":{"a":0,"k":[100,100,100],"ix":6}},"ao":0,"shapes":[{"ty":"gr","it":[{"ty":"rc","d":1,"s":{"a":0,"k":[1004,325],"ix":2},"p":{"a":0,"k":[0,0],"ix":3},"r":{"a":0,"k":25,"ix":4},"nm":"Rectangle Path 1","mn":"ADBE Vector Shape - Rect","hd":false},{"ty":"st","c":{"a":0,"k":[1,1,1,1],"ix":3},"o":{"a":0,"k":100,"ix":4},"w":{"a":0,"k":0,"ix":5},"lc":1,"lj":1,"ml":4,"bm":0,"nm":"Stroke 1","mn":"ADBE Vector Graphic - Stroke","hd":false},{"ty":"fl","c":{"a":0,"k":[0,0,0,1],"ix":4},"o":{"a":0,"k":100,"ix":5},"r":1,"bm":0,"nm":"Fill 1","mn":"ADBE Vector Graphic - Fill","hd":false},{"ty":"tr","p":{"a":0,"k":[-2.5,0],"ix":2},"a":{"a":0,"k":[0,0],"ix":1},"s":{"a":0,"k":[100,100],"ix":3},"r":{"a":0,"k":0,"ix":6},"o":{"a":0,"k":100,"ix":7},"sk":{"a":0,"k":0,"ix":4},"sa":{"a":0,"k":0,"ix":5},"nm":"Transform"}],"nm":"Rectangle 1","np":3,"cix":2,"bm":0,"ix":1,"mn":"ADBE Vector Group","hd":false}],"ip":0,"op":480,"st":0,"bm":9},{"ddd":0,"ind":22,"ty":4,"nm":"Wave","td":1,"sr":1,"ks":{"o":{"a":0,"k":100,"ix":11},"r":{"a":0,"k":0,"ix":10},"p":{"a":1,"k":[{"i":{"x":0.446,"y":1},"o":{"x":0.578,"y":0},"t":0,"s":[296.5,200,0],"to":[21.175,0,0],"ti":[17.523,0,0]},{"i":{"x":0.451,"y":1},"o":{"x":0.604,"y":0},"t":29,"s":[993.816,200,0],"to":[-15.871,0,0],"ti":[-40.438,0,0]},{"i":{"x":0.306,"y":1},"o":{"x":0.477,"y":0},"t":61,"s":[289.742,200,0],"to":[27.545,0,0],"ti":[3.667,-0.333,0]},{"t":76,"s":[659,200,0]}],"ix":2},"a":{"a":0,"k":[0,0,0],"ix":1},"s":{"a":0,"k":[100,100,100],"ix":6}},"ao":0,"shapes":[{"ty":"gr","it":[{"ty":"rc","d":1,"s":{"a":0,"k":[1260,882],"ix":2},"p":{"a":0,"k":[0,0],"ix":3},"r":{"a":0,"k":0,"ix":4},"nm":"Rectangle Path 1","mn":"ADBE Vector Shape - Rect","hd":false},{"ty":"st","c":{"a":0,"k":[0.2,0.2,0.2,1],"ix":3},"o":{"a":0,"k":100,"ix":4},"w":{"a":0,"k":0,"ix":5},"lc":1,"lj":1,"ml":4,"bm":0,"nm":"Stroke 1","mn":"ADBE Vector Graphic - Stroke","hd":false},{"ty":"fl","c":{"a":0,"k":[0,0,0,1],"ix":4},"o":{"a":0,"k":100,"ix":5},"r":1,"bm":0,"nm":"Fill 1","mn":"ADBE Vector Graphic - Fill","hd":false},{"ty":"tr","p":{"a":0,"k":[-626.5,-5],"ix":2},"a":{"a":0,"k":[0,0],"ix":1},"s":{"a":0,"k":[100,100],"ix":3},"r":{"a":0,"k":0,"ix":6},"o":{"a":0,"k":100,"ix":7},"sk":{"a":0,"k":0,"ix":4},"sa":{"a":0,"k":0,"ix":5},"nm":"Transform"}],"nm":"Rectangle 1","np":3,"cix":2,"bm":0,"ix":1,"mn":"ADBE Vector Group","hd":false}],"ip":0,"op":480,"st":0,"bm":0},{"ddd":0,"ind":23,"ty":4,"nm":"Side_01","tt":1,"sr":1,"ks":{"o":{"a":0,"k":100,"ix":11},"r":{"a":0,"k":0,"ix":10},"p":{"a":0,"k":[564.5,200,0],"ix":2},"a":{"a":0,"k":[0,0,0],"ix":1},"s":{"a":0,"k":[100,100,100],"ix":6}},"ao":0,"shapes":[{"ty":"gr","it":[{"ty":"rc","d":1,"s":{"a":0,"k":[1004,325],"ix":2},"p":{"a":0,"k":[0,0],"ix":3},"r":{"a":0,"k":25,"ix":4},"nm":"Rectangle Path 1","mn":"ADBE Vector Shape - Rect","hd":false},{"ty":"st","c":{"a":0,"k":[1,1,1,1],"ix":3},"o":{"a":0,"k":100,"ix":4},"w":{"a":0,"k":0,"ix":5},"lc":1,"lj":1,"ml":4,"bm":0,"nm":"Stroke 1","mn":"ADBE Vector Graphic - Stroke","hd":false},{"ty":"fl","c":{"a":0,"k":[0.529411764706,0.298039215686,0.243137254902,1],"ix":4},"o":{"a":0,"k":100,"ix":5},"r":1,"bm":0,"nm":"Fill 1","mn":"ADBE Vector Graphic - Fill","hd":false},{"ty":"tr","p":{"a":0,"k":[-2.5,0],"ix":2},"a":{"a":0,"k":[0,0],"ix":1},"s":{"a":0,"k":[100,100],"ix":3},"r":{"a":0,"k":0,"ix":6},"o":{"a":0,"k":100,"ix":7},"sk":{"a":0,"k":0,"ix":4},"sa":{"a":0,"k":0,"ix":5},"nm":"Transform"}],"nm":"Rectangle 1","np":3,"cix":2,"bm":0,"ix":1,"mn":"ADBE Vector Group","hd":false}],"ip":0,"op":480,"st":0,"bm":0},{"ddd":0,"ind":24,"ty":4,"nm":"Side_02","sr":1,"ks":{"o":{"a":0,"k":100,"ix":11},"r":{"a":0,"k":0,"ix":10},"p":{"a":0,"k":[564.5,200,0],"ix":2},"a":{"a":0,"k":[0,0,0],"ix":1},"s":{"a":0,"k":[100,100,100],"ix":6}},"ao":0,"shapes":[{"ty":"gr","it":[{"ty":"rc","d":1,"s":{"a":0,"k":[1004,325],"ix":2},"p":{"a":0,"k":[0,0],"ix":3},"r":{"a":0,"k":25,"ix":4},"nm":"Rectangle Path 1","mn":"ADBE Vector Shape - Rect","hd":false},{"ty":"st","c":{"a":0,"k":[1,1,1,1],"ix":3},"o":{"a":0,"k":100,"ix":4},"w":{"a":0,"k":0,"ix":5},"lc":1,"lj":1,"ml":4,"bm":0,"nm":"Stroke 1","mn":"ADBE Vector Graphic - Stroke","hd":false},{"ty":"fl","c":{"a":0,"k":[0.98431372549,0.923926798503,0.710249897078,1],"ix":4},"o":{"a":0,"k":100,"ix":5},"r":1,"bm":0,"nm":"Fill 1","mn":"ADBE Vector Graphic - Fill","hd":false},{"ty":"tr","p":{"a":0,"k":[-2.5,0],"ix":2},"a":{"a":0,"k":[0,0],"ix":1},"s":{"a":0,"k":[100,100],"ix":3},"r":{"a":0,"k":0,"ix":6},"o":{"a":0,"k":100,"ix":7},"sk":{"a":0,"k":0,"ix":4},"sa":{"a":0,"k":0,"ix":5},"nm":"Transform"}],"nm":"Rectangle 1","np":3,"cix":2,"bm":0,"ix":1,"mn":"ADBE Vector Group","hd":false}],"ip":0,"op":480,"st":0,"bm":0},{"ddd":0,"ind":25,"ty":1,"nm":"BG Guide","sr":1,"ks":{"o":{"a":0,"k":100,"ix":11},"r":{"a":0,"k":0,"ix":10},"p":{"a":0,"k":[562.5,200,0],"ix":2},"a":{"a":0,"k":[562.5,300,0],"ix":1},"s":{"a":0,"k":[100,100,100],"ix":6}},"ao":0,"sw":1125,"sh":600,"sc":"#ffffff","ip":0,"op":480,"st":0,"bm":0}]}],"layers":[{"ddd":0,"ind":1,"ty":4,"nm":"Line","sr":1,"ks":{"o":{"a":0,"k":100,"ix":11},"r":{"a":0,"k":0,"ix":10},"p":{"a":0,"k":[564.5,200,0],"ix":2},"a":{"a":0,"k":[0,0,0],"ix":1},"s":{"a":0,"k":[100,100,100],"ix":6}},"ao":0,"shapes":[{"ty":"gr","it":[{"ty":"rc","d":1,"s":{"a":0,"k":[1004,325],"ix":2},"p":{"a":0,"k":[0,0],"ix":3},"r":{"a":0,"k":25,"ix":4},"nm":"Rectangle Path 1","mn":"ADBE Vector Shape - Rect","hd":false},{"ty":"st","c":{"a":0,"k":[0.2,0.2,0.2,1],"ix":3},"o":{"a":0,"k":100,"ix":4},"w":{"a":0,"k":5,"ix":5},"lc":1,"lj":1,"ml":4,"bm":0,"nm":"Stroke 1","mn":"ADBE Vector Graphic - Stroke","hd":false},{"ty":"tr","p":{"a":0,"k":[-2.5,0],"ix":2},"a":{"a":0,"k":[0,0],"ix":1},"s":{"a":0,"k":[100,100],"ix":3},"r":{"a":0,"k":0,"ix":6},"o":{"a":0,"k":100,"ix":7},"sk":{"a":0,"k":0,"ix":4},"sa":{"a":0,"k":0,"ix":5},"nm":"Transform"}],"nm":"Rectangle 1","np":3,"cix":2,"bm":0,"ix":1,"mn":"ADBE Vector Group","hd":false}],"ip":0,"op":480,"st":0,"bm":0},{"ddd":0,"ind":2,"ty":4,"nm":"Side_02","td":1,"sr":1,"ks":{"o":{"a":0,"k":100,"ix":11},"r":{"a":0,"k":0,"ix":10},"p":{"a":0,"k":[564.5,200,0],"ix":2},"a":{"a":0,"k":[0,0,0],"ix":1},"s":{"a":0,"k":[100,100,100],"ix":6}},"ao":0,"shapes":[{"ty":"gr","it":[{"ty":"rc","d":1,"s":{"a":0,"k":[1004,325],"ix":2},"p":{"a":0,"k":[0,0],"ix":3},"r":{"a":0,"k":25,"ix":4},"nm":"Rectangle Path 1","mn":"ADBE Vector Shape - Rect","hd":false},{"ty":"st","c":{"a":0,"k":[1,1,1,1],"ix":3},"o":{"a":0,"k":100,"ix":4},"w":{"a":0,"k":0,"ix":5},"lc":1,"lj":1,"ml":4,"bm":0,"nm":"Stroke 1","mn":"ADBE Vector Graphic - Stroke","hd":false},{"ty":"fl","c":{"a":0,"k":[0.98431372549,0.923926798503,0.710249897078,1],"ix":4},"o":{"a":0,"k":100,"ix":5},"r":1,"bm":0,"nm":"Fill 1","mn":"ADBE Vector Graphic - Fill","hd":false},{"ty":"tr","p":{"a":0,"k":[-2.5,0],"ix":2},"a":{"a":0,"k":[0,0],"ix":1},"s":{"a":0,"k":[100,100],"ix":3},"r":{"a":0,"k":0,"ix":6},"o":{"a":0,"k":100,"ix":7},"sk":{"a":0,"k":0,"ix":4},"sa":{"a":0,"k":0,"ix":5},"nm":"Transform"}],"nm":"Rectangle 1","np":3,"cix":2,"bm":0,"ix":1,"mn":"ADBE Vector Group","hd":false}],"ip":0,"op":480,"st":0,"bm":0},{"ddd":0,"ind":3,"ty":0,"nm":"[60/40]우정지수_3배수","tt":1,"refId":"comp_0","sr":1,"ks":{"o":{"a":0,"k":100,"ix":11},"r":{"a":0,"k":0,"ix":10},"p":{"a":0,"k":[562.5,200,0],"ix":2},"a":{"a":0,"k":[562.5,200,0],"ix":1},"s":{"a":0,"k":[100,100,100],"ix":6}},"ao":0,"w":1125,"h":400,"ip":0,"op":480,"st":0,"bm":0}],"markers":[]}