{"v":"4.8.0","meta":{"g":"LottieFiles AE ","a":"","k":"","d":"","tc":""},"fr":30,"ip":0,"op":60,"w":214,"h":267,"nm":"활용법_커피담당","ddd":0,"assets":[],"layers":[{"ddd":0,"ind":1,"ty":4,"nm":"Hand 2","parent":4,"sr":1,"ks":{"o":{"a":0,"k":100,"ix":11},"r":{"a":0,"k":0,"ix":10},"p":{"a":1,"k":[{"i":{"x":0.341,"y":1},"o":{"x":0.333,"y":0},"t":10,"s":[259.825,-17.676,0],"to":[0,0,0],"ti":[0,0,0]},{"t":23,"s":[99.825,-17.676,0]}],"ix":2},"a":{"a":0,"k":[74.892,64.925,0],"ix":1},"s":{"a":0,"k":[100,100,100],"ix":6}},"ao":0,"shapes":[{"ty":"gr","it":[{"ind":0,"ty":"sh","ix":1,"ks":{"a":0,"k":{"i":[[0,0],[-0.468,-3.249],[-1.772,-7.973],[-3.88,0.445],[-18.389,2.388],[0.599,4.435],[0,0],[4.974,-2.931]],"o":[[-2.828,1.666],[1.142,7.925],[0.846,3.812],[17.231,-1.976],[4.438,-0.577],[0,0],[-0.773,-5.721],[0,0]],"v":[[-34.367,-1.438],[-38.258,6.684],[-32.509,35.809],[-24.204,41.732],[56.773,32.141],[63.728,23.054],[55.055,-41.129],[42.955,-47.004]],"c":true},"ix":2},"nm":"Path 1","mn":"ADBE Vector Shape - Group","hd":false},{"ty":"fl","c":{"a":0,"k":[0.349019607843,0.403921598547,0.549019607843,1],"ix":4},"o":{"a":0,"k":100,"ix":5},"r":1,"bm":0,"nm":"Fill 1","mn":"ADBE Vector Graphic - Fill","hd":false},{"ty":"tr","p":{"a":0,"k":[107.604,50.185],"ix":2},"a":{"a":0,"k":[0,0],"ix":1},"s":{"a":0,"k":[100,100],"ix":3},"r":{"a":0,"k":0,"ix":6},"o":{"a":0,"k":100,"ix":7},"sk":{"a":0,"k":0,"ix":4},"sa":{"a":0,"k":0,"ix":5},"nm":"Transform"}],"nm":"Group 1","np":2,"cix":2,"bm":0,"ix":1,"mn":"ADBE Vector Group","hd":false},{"ty":"gr","it":[{"ind":0,"ty":"sh","ix":1,"ks":{"a":0,"k":{"i":[[0,0],[-9.037,3.852]],"o":[[1.482,-0.889],[0,0]],"v":[[-7.111,4.518],[7.111,-4.518]],"c":false},"ix":2},"nm":"Path 1","mn":"ADBE Vector Shape - Group","hd":false},{"ty":"st","c":{"a":0,"k":[1,0.752941236309,0.639215686275,1],"ix":3},"o":{"a":0,"k":100,"ix":4},"w":{"a":0,"k":3,"ix":5},"lc":2,"lj":2,"bm":0,"nm":"Stroke 1","mn":"ADBE Vector Graphic - Stroke","hd":false},{"ty":"tr","p":{"a":0,"k":[38.176,109.893],"ix":2},"a":{"a":0,"k":[0,0],"ix":1},"s":{"a":0,"k":[100,100],"ix":3},"r":{"a":0,"k":0,"ix":6},"o":{"a":0,"k":100,"ix":7},"sk":{"a":0,"k":0,"ix":4},"sa":{"a":0,"k":0,"ix":5},"nm":"Transform"}],"nm":"Group 2","np":2,"cix":2,"bm":0,"ix":2,"mn":"ADBE Vector Group","hd":false},{"ty":"gr","it":[{"ind":0,"ty":"sh","ix":1,"ks":{"a":0,"k":{"i":[[0,0],[-6.074,1.185]],"o":[[0.741,-0.741],[0,0]],"v":[[-8.37,4.445],[8.37,-4.445]],"c":false},"ix":2},"nm":"Path 1","mn":"ADBE Vector Shape - Group","hd":false},{"ty":"st","c":{"a":0,"k":[1,0.752941236309,0.639215686275,1],"ix":3},"o":{"a":0,"k":100,"ix":4},"w":{"a":0,"k":3,"ix":5},"lc":2,"lj":2,"bm":0,"nm":"Stroke 1","mn":"ADBE Vector Graphic - Stroke","hd":false},{"ty":"tr","p":{"a":0,"k":[20.473,105.374],"ix":2},"a":{"a":0,"k":[0,0],"ix":1},"s":{"a":0,"k":[100,100],"ix":3},"r":{"a":0,"k":0,"ix":6},"o":{"a":0,"k":100,"ix":7},"sk":{"a":0,"k":0,"ix":4},"sa":{"a":0,"k":0,"ix":5},"nm":"Transform"}],"nm":"Group 3","np":2,"cix":2,"bm":0,"ix":3,"mn":"ADBE Vector Group","hd":false},{"ty":"gr","it":[{"ind":0,"ty":"sh","ix":1,"ks":{"a":0,"k":{"i":[[0,0],[-6.666,1.629]],"o":[[0.889,-0.444],[0,0]],"v":[[-6.666,4.222],[6.666,-4.222]],"c":false},"ix":2},"nm":"Path 1","mn":"ADBE Vector Shape - Group","hd":false},{"ty":"st","c":{"a":0,"k":[1,0.752941236309,0.639215686275,1],"ix":3},"o":{"a":0,"k":100,"ix":4},"w":{"a":0,"k":3,"ix":5},"lc":2,"lj":2,"bm":0,"nm":"Stroke 1","mn":"ADBE Vector Graphic - Stroke","hd":false},{"ty":"tr","p":{"a":0,"k":[16.843,91.967],"ix":2},"a":{"a":0,"k":[0,0],"ix":1},"s":{"a":0,"k":[100,100],"ix":3},"r":{"a":0,"k":0,"ix":6},"o":{"a":0,"k":100,"ix":7},"sk":{"a":0,"k":0,"ix":4},"sa":{"a":0,"k":0,"ix":5},"nm":"Transform"}],"nm":"Group 4","np":2,"cix":2,"bm":0,"ix":4,"mn":"ADBE Vector Group","hd":false},{"ty":"gr","it":[{"ind":0,"ty":"sh","ix":1,"ks":{"a":0,"k":{"i":[[0,0],[-2.963,0]],"o":[[0,0],[0,0]],"v":[[-4.741,2.222],[4.741,-2.222]],"c":false},"ix":2},"nm":"Path 1","mn":"ADBE Vector Shape - Group","hd":false},{"ty":"st","c":{"a":0,"k":[1,0.752941236309,0.639215686275,1],"ix":3},"o":{"a":0,"k":100,"ix":4},"w":{"a":0,"k":3,"ix":5},"lc":2,"lj":2,"bm":0,"nm":"Stroke 1","mn":"ADBE Vector Graphic - Stroke","hd":false},{"ty":"tr","p":{"a":0,"k":[14.917,77.967],"ix":2},"a":{"a":0,"k":[0,0],"ix":1},"s":{"a":0,"k":[100,100],"ix":3},"r":{"a":0,"k":0,"ix":6},"o":{"a":0,"k":100,"ix":7},"sk":{"a":0,"k":0,"ix":4},"sa":{"a":0,"k":0,"ix":5},"nm":"Transform"}],"nm":"Group 5","np":2,"cix":2,"bm":0,"ix":5,"mn":"ADBE Vector Group","hd":false},{"ty":"gr","it":[{"ind":0,"ty":"sh","ix":1,"ks":{"a":0,"k":{"i":[[0,0],[4.717,0.147],[0.885,-17.833],[-3.831,-5.159],[0,0],[-9.285,-5.748],[-3.684,-2.653],[-2.21,1.327],[-6.799,0.585],[-1.179,8.106],[-0.339,1.514],[-4.348,2.079],[0,0]],"o":[[0,0],[-4.716,-0.147],[-0.737,1.622],[1.327,1.916],[0,0],[-2.21,6.19],[3.685,2.653],[1.032,1.769],[6.799,-0.585],[0.276,-1.9],[1.053,-4.702],[0,0],[0,0]],"v":[[35.078,-33.161],[2.948,-25.497],[-38.615,-7.664],[-40.089,3.685],[-36.404,6.043],[-35.52,20.192],[-34.046,30.508],[-15.918,26.529],[-3.262,31.241],[16.949,11.938],[17.892,6.808],[26.477,-3.912],[44.805,-12.675]],"c":true},"ix":2},"nm":"Path 1","mn":"ADBE Vector Shape - Group","hd":false},{"ty":"fl","c":{"a":0,"k":[1,0.831372608858,0.756862804936,1],"ix":4},"o":{"a":0,"k":100,"ix":5},"r":1,"bm":0,"nm":"Fill 1","mn":"ADBE Vector Graphic - Fill","hd":false},{"ty":"tr","p":{"a":0,"k":[45.055,90.536],"ix":2},"a":{"a":0,"k":[0,0],"ix":1},"s":{"a":0,"k":[100,100],"ix":3},"r":{"a":0,"k":0,"ix":6},"o":{"a":0,"k":100,"ix":7},"sk":{"a":0,"k":0,"ix":4},"sa":{"a":0,"k":0,"ix":5},"nm":"Transform"}],"nm":"Group 6","np":2,"cix":2,"bm":0,"ix":6,"mn":"ADBE Vector Group","hd":false}],"ip":33,"op":60,"st":18,"bm":0},{"ddd":0,"ind":2,"ty":4,"nm":"Hand 3","sr":1,"ks":{"o":{"a":0,"k":100,"ix":11},"r":{"a":0,"k":0,"ix":10},"p":{"a":1,"k":[{"i":{"x":0.341,"y":1},"o":{"x":0.333,"y":0},"t":17,"s":[292.062,56.917,0],"to":[0,0,0],"ti":[0,0,0]},{"t":30,"s":[132.062,56.917,0]}],"ix":2},"a":{"a":0,"k":[74.892,64.925,0],"ix":1},"s":{"a":0,"k":[100,100,100],"ix":6}},"ao":0,"shapes":[{"ty":"gr","it":[{"ind":0,"ty":"sh","ix":1,"ks":{"a":0,"k":{"i":[[0,0],[-0.468,-3.249],[-1.772,-7.973],[-3.88,0.445],[-18.389,2.388],[0.599,4.435],[0,0],[4.974,-2.931]],"o":[[-2.828,1.666],[1.142,7.925],[0.846,3.812],[17.231,-1.976],[4.438,-0.577],[0,0],[-0.773,-5.721],[0,0]],"v":[[-34.367,-1.438],[-38.258,6.684],[-32.509,35.809],[-24.204,41.732],[56.773,32.141],[63.728,23.054],[55.055,-41.129],[42.955,-47.004]],"c":true},"ix":2},"nm":"Path 1","mn":"ADBE Vector Shape - Group","hd":false},{"ty":"fl","c":{"a":0,"k":[0.349019607843,0.403921598547,0.549019607843,1],"ix":4},"o":{"a":0,"k":100,"ix":5},"r":1,"bm":0,"nm":"Fill 1","mn":"ADBE Vector Graphic - Fill","hd":false},{"ty":"tr","p":{"a":0,"k":[107.604,50.185],"ix":2},"a":{"a":0,"k":[0,0],"ix":1},"s":{"a":0,"k":[100,100],"ix":3},"r":{"a":0,"k":0,"ix":6},"o":{"a":0,"k":100,"ix":7},"sk":{"a":0,"k":0,"ix":4},"sa":{"a":0,"k":0,"ix":5},"nm":"Transform"}],"nm":"Group 1","np":2,"cix":2,"bm":0,"ix":1,"mn":"ADBE Vector Group","hd":false},{"ty":"gr","it":[{"ind":0,"ty":"sh","ix":1,"ks":{"a":0,"k":{"i":[[0,0],[-9.037,3.852]],"o":[[1.482,-0.889],[0,0]],"v":[[-7.111,4.518],[7.111,-4.518]],"c":false},"ix":2},"nm":"Path 1","mn":"ADBE Vector Shape - Group","hd":false},{"ty":"st","c":{"a":0,"k":[1,0.752941236309,0.639215686275,1],"ix":3},"o":{"a":0,"k":100,"ix":4},"w":{"a":0,"k":3,"ix":5},"lc":2,"lj":2,"bm":0,"nm":"Stroke 1","mn":"ADBE Vector Graphic - Stroke","hd":false},{"ty":"tr","p":{"a":0,"k":[38.176,109.893],"ix":2},"a":{"a":0,"k":[0,0],"ix":1},"s":{"a":0,"k":[100,100],"ix":3},"r":{"a":0,"k":0,"ix":6},"o":{"a":0,"k":100,"ix":7},"sk":{"a":0,"k":0,"ix":4},"sa":{"a":0,"k":0,"ix":5},"nm":"Transform"}],"nm":"Group 2","np":2,"cix":2,"bm":0,"ix":2,"mn":"ADBE Vector Group","hd":false},{"ty":"gr","it":[{"ind":0,"ty":"sh","ix":1,"ks":{"a":0,"k":{"i":[[0,0],[-6.074,1.185]],"o":[[0.741,-0.741],[0,0]],"v":[[-8.37,4.445],[8.37,-4.445]],"c":false},"ix":2},"nm":"Path 1","mn":"ADBE Vector Shape - Group","hd":false},{"ty":"st","c":{"a":0,"k":[1,0.752941236309,0.639215686275,1],"ix":3},"o":{"a":0,"k":100,"ix":4},"w":{"a":0,"k":3,"ix":5},"lc":2,"lj":2,"bm":0,"nm":"Stroke 1","mn":"ADBE Vector Graphic - Stroke","hd":false},{"ty":"tr","p":{"a":0,"k":[20.473,105.374],"ix":2},"a":{"a":0,"k":[0,0],"ix":1},"s":{"a":0,"k":[100,100],"ix":3},"r":{"a":0,"k":0,"ix":6},"o":{"a":0,"k":100,"ix":7},"sk":{"a":0,"k":0,"ix":4},"sa":{"a":0,"k":0,"ix":5},"nm":"Transform"}],"nm":"Group 3","np":2,"cix":2,"bm":0,"ix":3,"mn":"ADBE Vector Group","hd":false},{"ty":"gr","it":[{"ind":0,"ty":"sh","ix":1,"ks":{"a":0,"k":{"i":[[0,0],[-6.666,1.629]],"o":[[0.889,-0.444],[0,0]],"v":[[-6.666,4.222],[6.666,-4.222]],"c":false},"ix":2},"nm":"Path 1","mn":"ADBE Vector Shape - Group","hd":false},{"ty":"st","c":{"a":0,"k":[1,0.752941236309,0.639215686275,1],"ix":3},"o":{"a":0,"k":100,"ix":4},"w":{"a":0,"k":3,"ix":5},"lc":2,"lj":2,"bm":0,"nm":"Stroke 1","mn":"ADBE Vector Graphic - Stroke","hd":false},{"ty":"tr","p":{"a":0,"k":[16.843,91.967],"ix":2},"a":{"a":0,"k":[0,0],"ix":1},"s":{"a":0,"k":[100,100],"ix":3},"r":{"a":0,"k":0,"ix":6},"o":{"a":0,"k":100,"ix":7},"sk":{"a":0,"k":0,"ix":4},"sa":{"a":0,"k":0,"ix":5},"nm":"Transform"}],"nm":"Group 4","np":2,"cix":2,"bm":0,"ix":4,"mn":"ADBE Vector Group","hd":false},{"ty":"gr","it":[{"ind":0,"ty":"sh","ix":1,"ks":{"a":0,"k":{"i":[[0,0],[-2.963,0]],"o":[[0,0],[0,0]],"v":[[-4.741,2.222],[4.741,-2.222]],"c":false},"ix":2},"nm":"Path 1","mn":"ADBE Vector Shape - Group","hd":false},{"ty":"st","c":{"a":0,"k":[1,0.752941236309,0.639215686275,1],"ix":3},"o":{"a":0,"k":100,"ix":4},"w":{"a":0,"k":3,"ix":5},"lc":2,"lj":2,"bm":0,"nm":"Stroke 1","mn":"ADBE Vector Graphic - Stroke","hd":false},{"ty":"tr","p":{"a":0,"k":[14.917,77.967],"ix":2},"a":{"a":0,"k":[0,0],"ix":1},"s":{"a":0,"k":[100,100],"ix":3},"r":{"a":0,"k":0,"ix":6},"o":{"a":0,"k":100,"ix":7},"sk":{"a":0,"k":0,"ix":4},"sa":{"a":0,"k":0,"ix":5},"nm":"Transform"}],"nm":"Group 5","np":2,"cix":2,"bm":0,"ix":5,"mn":"ADBE Vector Group","hd":false},{"ty":"gr","it":[{"ind":0,"ty":"sh","ix":1,"ks":{"a":0,"k":{"i":[[0,0],[4.717,0.147],[0.885,-17.833],[-3.831,-5.159],[0,0],[-9.285,-5.748],[-3.684,-2.653],[-2.21,1.327],[-6.799,0.585],[-1.179,8.106],[-0.339,1.514],[-4.348,2.079],[0,0]],"o":[[0,0],[-4.716,-0.147],[-0.737,1.622],[1.327,1.916],[0,0],[-2.21,6.19],[3.685,2.653],[1.032,1.769],[6.799,-0.585],[0.276,-1.9],[1.053,-4.702],[0,0],[0,0]],"v":[[35.078,-33.161],[2.948,-25.497],[-38.615,-7.664],[-40.089,3.685],[-36.404,6.043],[-35.52,20.192],[-34.046,30.508],[-15.918,26.529],[-3.262,31.241],[16.949,11.938],[17.892,6.808],[26.477,-3.912],[44.805,-12.675]],"c":true},"ix":2},"nm":"Path 1","mn":"ADBE Vector Shape - Group","hd":false},{"ty":"fl","c":{"a":0,"k":[1,0.831372608858,0.756862804936,1],"ix":4},"o":{"a":0,"k":100,"ix":5},"r":1,"bm":0,"nm":"Fill 1","mn":"ADBE Vector Graphic - Fill","hd":false},{"ty":"tr","p":{"a":0,"k":[45.055,90.536],"ix":2},"a":{"a":0,"k":[0,0],"ix":1},"s":{"a":0,"k":[100,100],"ix":3},"r":{"a":0,"k":0,"ix":6},"o":{"a":0,"k":100,"ix":7},"sk":{"a":0,"k":0,"ix":4},"sa":{"a":0,"k":0,"ix":5},"nm":"Transform"}],"nm":"Group 6","np":2,"cix":2,"bm":0,"ix":6,"mn":"ADBE Vector Group","hd":false}],"ip":30,"op":33,"st":25,"bm":0},{"ddd":0,"ind":3,"ty":4,"nm":"Hand","sr":1,"ks":{"o":{"a":0,"k":100,"ix":11},"r":{"a":0,"k":0,"ix":10},"p":{"a":1,"k":[{"i":{"x":0.667,"y":1},"o":{"x":0.167,"y":0.167},"t":19,"s":[295.062,20.417,0],"to":[-55.562,-9.167,0],"ti":[21.938,-22.417,0]},{"t":32,"s":[132.062,56.917,0]}],"ix":2},"a":{"a":0,"k":[74.892,64.925,0],"ix":1},"s":{"a":0,"k":[100,100,100],"ix":6}},"ao":0,"shapes":[{"ty":"gr","it":[{"ind":0,"ty":"sh","ix":1,"ks":{"a":0,"k":{"i":[[0,0],[-0.468,-3.249],[-1.772,-7.973],[-3.88,0.445],[-18.389,2.388],[0.599,4.435],[0,0],[4.974,-2.931]],"o":[[-2.828,1.666],[1.142,7.925],[0.846,3.812],[17.231,-1.976],[4.438,-0.577],[0,0],[-0.773,-5.721],[0,0]],"v":[[-34.367,-1.438],[-38.258,6.684],[-32.509,35.809],[-24.204,41.732],[56.773,32.141],[63.728,23.054],[55.055,-41.129],[42.955,-47.004]],"c":true},"ix":2},"nm":"Path 1","mn":"ADBE Vector Shape - Group","hd":false},{"ty":"fl","c":{"a":0,"k":[0.349019607843,0.403921598547,0.549019607843,1],"ix":4},"o":{"a":0,"k":100,"ix":5},"r":1,"bm":0,"nm":"Fill 1","mn":"ADBE Vector Graphic - Fill","hd":false},{"ty":"tr","p":{"a":0,"k":[107.604,50.185],"ix":2},"a":{"a":0,"k":[0,0],"ix":1},"s":{"a":0,"k":[100,100],"ix":3},"r":{"a":0,"k":0,"ix":6},"o":{"a":0,"k":100,"ix":7},"sk":{"a":0,"k":0,"ix":4},"sa":{"a":0,"k":0,"ix":5},"nm":"Transform"}],"nm":"Group 1","np":2,"cix":2,"bm":0,"ix":1,"mn":"ADBE Vector Group","hd":false},{"ty":"gr","it":[{"ind":0,"ty":"sh","ix":1,"ks":{"a":0,"k":{"i":[[0,0],[-9.266,3.263]],"o":[[1.536,-0.792],[0,0]],"v":[[-11.499,4.183],[2.468,-4.036]],"c":false},"ix":2},"nm":"Path 1","mn":"ADBE Vector Shape - Group","hd":false},{"ty":"st","c":{"a":0,"k":[1,0.752941236309,0.639215686275,1],"ix":3},"o":{"a":0,"k":100,"ix":4},"w":{"a":0,"k":3,"ix":5},"lc":2,"lj":2,"bm":0,"nm":"Stroke 1","mn":"ADBE Vector Graphic - Stroke","hd":false},{"ty":"tr","p":{"a":0,"k":[38.176,109.893],"ix":2},"a":{"a":0,"k":[0,0],"ix":1},"s":{"a":0,"k":[100,100],"ix":3},"r":{"a":0,"k":0,"ix":6},"o":{"a":0,"k":100,"ix":7},"sk":{"a":0,"k":0,"ix":4},"sa":{"a":0,"k":0,"ix":5},"nm":"Transform"}],"nm":"Group 2","np":2,"cix":2,"bm":0,"ix":2,"mn":"ADBE Vector Group","hd":false},{"ty":"gr","it":[{"ind":0,"ty":"sh","ix":1,"ks":{"a":0,"k":{"i":[[0,0],[-6.138,0.792]],"o":[[0.787,-0.692],[0,0]],"v":[[-20.007,2.975],[1.399,-2.8]],"c":false},"ix":2},"nm":"Path 1","mn":"ADBE Vector Shape - Group","hd":false},{"ty":"st","c":{"a":0,"k":[1,0.752941236309,0.639215686275,1],"ix":3},"o":{"a":0,"k":100,"ix":4},"w":{"a":0,"k":3,"ix":5},"lc":2,"lj":2,"bm":0,"nm":"Stroke 1","mn":"ADBE Vector Graphic - Stroke","hd":false},{"ty":"tr","p":{"a":0,"k":[20.473,105.374],"ix":2},"a":{"a":0,"k":[0,0],"ix":1},"s":{"a":0,"k":[100,100],"ix":3},"r":{"a":0,"k":0,"ix":6},"o":{"a":0,"k":100,"ix":7},"sk":{"a":0,"k":0,"ix":4},"sa":{"a":0,"k":0,"ix":5},"nm":"Transform"}],"nm":"Group 3","np":2,"cix":2,"bm":0,"ix":3,"mn":"ADBE Vector Group","hd":false},{"ty":"gr","it":[{"ind":0,"ty":"sh","ix":1,"ks":{"a":0,"k":{"i":[[0,0],[-6.757,1.197]],"o":[[0.916,-0.386],[0,0]],"v":[[-18.477,3.465],[1.395,-2.338]],"c":false},"ix":2},"nm":"Path 1","mn":"ADBE Vector Shape - Group","hd":false},{"ty":"st","c":{"a":0,"k":[1,0.752941236309,0.639215686275,1],"ix":3},"o":{"a":0,"k":100,"ix":4},"w":{"a":0,"k":3,"ix":5},"lc":2,"lj":2,"bm":0,"nm":"Stroke 1","mn":"ADBE Vector Graphic - Stroke","hd":false},{"ty":"tr","p":{"a":0,"k":[16.843,91.967],"ix":2},"a":{"a":0,"k":[0,0],"ix":1},"s":{"a":0,"k":[100,100],"ix":3},"r":{"a":0,"k":0,"ix":6},"o":{"a":0,"k":100,"ix":7},"sk":{"a":0,"k":0,"ix":4},"sa":{"a":0,"k":0,"ix":5},"nm":"Transform"}],"nm":"Group 4","np":2,"cix":2,"bm":0,"ix":4,"mn":"ADBE Vector Group","hd":false},{"ty":"gr","it":[{"ind":0,"ty":"sh","ix":1,"ks":{"a":0,"k":{"i":[[0,0],[-2.957,-0.19]],"o":[[0,0],[0,0]],"v":[[-9.853,0.987],[4.357,-4.054]],"c":false},"ix":2},"nm":"Path 1","mn":"ADBE Vector Shape - Group","hd":false},{"ty":"st","c":{"a":0,"k":[1,0.752941236309,0.639215686275,1],"ix":3},"o":{"a":0,"k":100,"ix":4},"w":{"a":0,"k":3,"ix":5},"lc":2,"lj":2,"bm":0,"nm":"Stroke 1","mn":"ADBE Vector Graphic - Stroke","hd":false},{"ty":"tr","p":{"a":0,"k":[14.917,77.967],"ix":2},"a":{"a":0,"k":[0,0],"ix":1},"s":{"a":0,"k":[100,100],"ix":3},"r":{"a":0,"k":0,"ix":6},"o":{"a":0,"k":100,"ix":7},"sk":{"a":0,"k":0,"ix":4},"sa":{"a":0,"k":0,"ix":5},"nm":"Transform"}],"nm":"Group 5","np":2,"cix":2,"bm":0,"ix":5,"mn":"ADBE Vector Group","hd":false},{"ty":"gr","it":[{"ind":0,"ty":"sh","ix":1,"ks":{"a":0,"k":{"i":[[0,0],[4.717,0.147],[9.277,-10.198],[-8.243,3.489],[-3.177,-9.436],[-12.862,3.861],[-3.071,-7.488],[-10.687,2.699],[2.018,-2.267],[-18.932,5.007],[-2.291,1.182],[-6.899,-4.137],[-3.451,1.388],[-1.179,8.106],[-0.339,1.514],[-4.348,2.079],[0,0]],"o":[[0,0],[-3.983,-0.124],[-1.707,1.877],[-0.84,1.571],[2.441,4.454],[-9.893,2.496],[2.17,5.292],[-5.092,1.707],[-0.967,1.086],[4.39,-1.161],[-3.784,1.203],[2.189,1.313],[6.331,-2.547],[0.276,-1.9],[1.053,-4.702],[0,0],[0,0]],"v":[[35.077,-33.161],[2.947,-25.497],[-44.913,-17.326],[-38.834,-11.826],[-56.542,2.915],[-37.509,1.995],[-58.676,16.077],[-37.536,16.172],[-51.877,21.558],[-35.087,28.296],[-18.382,23.756],[-19.318,35.599],[-4.482,30.125],[16.949,11.937],[17.892,6.808],[26.476,-3.912],[44.804,-12.675]],"c":true},"ix":2},"nm":"Path 1","mn":"ADBE Vector Shape - Group","hd":false},{"ty":"fl","c":{"a":0,"k":[1,0.831372608858,0.756862804936,1],"ix":4},"o":{"a":0,"k":100,"ix":5},"r":1,"bm":0,"nm":"Fill 1","mn":"ADBE Vector Graphic - Fill","hd":false},{"ty":"tr","p":{"a":0,"k":[45.055,90.536],"ix":2},"a":{"a":0,"k":[0,0],"ix":1},"s":{"a":0,"k":[100,100],"ix":3},"r":{"a":0,"k":0,"ix":6},"o":{"a":0,"k":100,"ix":7},"sk":{"a":0,"k":0,"ix":4},"sa":{"a":0,"k":0,"ix":5},"nm":"Transform"}],"nm":"Group 6","np":2,"cix":2,"bm":0,"ix":6,"mn":"ADBE Vector Group","hd":false}],"ip":19,"op":30,"st":27,"bm":0},{"ddd":0,"ind":4,"ty":3,"nm":"Null 60","sr":1,"ks":{"o":{"a":0,"k":0,"ix":11},"r":{"a":0,"k":0,"ix":10},"p":{"a":1,"k":[{"i":{"x":0.046,"y":1},"o":{"x":0.333,"y":0},"t":0,"s":[-97.763,124.593,0],"to":[30,0,0],"ti":[-30,0,0]},{"i":{"x":0.306,"y":0.306},"o":{"x":0.167,"y":0.167},"t":19,"s":[82.237,124.593,0],"to":[0,0,0],"ti":[0,0,0]},{"i":{"x":0.521,"y":1},"o":{"x":0.418,"y":0},"t":33,"s":[82.237,124.593,0],"to":[51.667,-44.833,0],"ti":[-65.924,-2.78,0]},{"t":50,"s":[293.237,53.593,0]}],"ix":2},"a":{"a":0,"k":[50,50,0],"ix":1},"s":{"a":0,"k":[100,100,100],"ix":6}},"ao":0,"ip":0,"op":60,"st":0,"bm":0},{"ddd":0,"ind":5,"ty":4,"nm":"Handle","parent":4,"sr":1,"ks":{"o":{"a":0,"k":100,"ix":11},"r":{"a":0,"k":0,"ix":10},"p":{"a":0,"k":[49.773,11.023,0],"ix":2},"a":{"a":0,"k":[4.25,31.925,0],"ix":1},"s":{"a":0,"k":[100,100,100],"ix":6}},"ao":0,"shapes":[{"ty":"gr","it":[{"ind":0,"ty":"sh","ix":1,"ks":{"a":0,"k":{"i":[[0,-2.21],[0,0],[1.41,0],[1.24,-0.5],[0,0],[-2.2,0]],"o":[[0,0],[-1.24,-0.5],[-1.41,0],[0,0],[0,-2.21],[2.21,0]],"v":[[4,-27.675],[4,31.675],[0,30.905],[-4,31.675],[-4,-27.675],[0,-31.675]],"c":true},"ix":2},"nm":"Path 1","mn":"ADBE Vector Shape - Group","hd":false},{"ty":"fl","c":{"a":0,"k":[0.349019607843,0.290196078431,0.223529426724,1],"ix":4},"o":{"a":0,"k":100,"ix":5},"r":1,"bm":0,"nm":"Fill 1","mn":"ADBE Vector Graphic - Fill","hd":false},{"ty":"tr","p":{"a":0,"k":[4.25,31.925],"ix":2},"a":{"a":0,"k":[0,0],"ix":1},"s":{"a":0,"k":[100,100],"ix":3},"r":{"a":0,"k":0,"ix":6},"o":{"a":0,"k":100,"ix":7},"sk":{"a":0,"k":0,"ix":4},"sa":{"a":0,"k":0,"ix":5},"nm":"Transform"}],"nm":"Group 1","np":2,"cix":2,"bm":0,"ix":1,"mn":"ADBE Vector Group","hd":false}],"ip":0,"op":60,"st":0,"bm":0},{"ddd":0,"ind":6,"ty":4,"nm":"Cup_02","parent":4,"sr":1,"ks":{"o":{"a":0,"k":100,"ix":11},"r":{"a":0,"k":0,"ix":10},"p":{"a":0,"k":[89.537,81.699,0],"ix":2},"a":{"a":0,"k":[27.14,24.858,0],"ix":1},"s":{"a":0,"k":[100,100,100],"ix":6}},"ao":0,"shapes":[{"ty":"gr","it":[{"ind":0,"ty":"sh","ix":1,"ks":{"a":0,"k":{"i":[[0.89,0],[0,0],[0,0.89],[0,0],[-0.89,0],[0,-0.889],[0,0]],"o":[[0,0],[-0.89,0],[0,0],[0,-0.889],[0.89,0],[0,0],[0,0.89]],"v":[[0,2.889],[0,2.889],[-1.611,1.278],[-1.611,-1.278],[0,-2.889],[1.611,-1.278],[1.611,1.278]],"c":true},"ix":2},"nm":"Path 1","mn":"ADBE Vector Shape - Group","hd":false},{"ty":"fl","c":{"a":0,"k":[0.325490196078,0.250980392157,0.203921583587,1],"ix":4},"o":{"a":0,"k":100,"ix":5},"r":1,"bm":0,"nm":"Fill 1","mn":"ADBE Vector Graphic - Fill","hd":false},{"ty":"tr","p":{"a":0,"k":[37.421,10.139],"ix":2},"a":{"a":0,"k":[0,0],"ix":1},"s":{"a":0,"k":[100,100],"ix":3},"r":{"a":0,"k":0,"ix":6},"o":{"a":0,"k":100,"ix":7},"sk":{"a":0,"k":0,"ix":4},"sa":{"a":0,"k":0,"ix":5},"nm":"Transform"}],"nm":"Group 1","np":2,"cix":2,"bm":0,"ix":1,"mn":"ADBE Vector Group","hd":false},{"ty":"gr","it":[{"ind":0,"ty":"sh","ix":1,"ks":{"a":0,"k":{"i":[[-7.594,0],[-2.276,4.531],[0.053,0.29],[0,0],[8.301,0],[0.605,5.081],[0,0],[0,0],[-0.137,-0.265]],"o":[[7.648,0],[0.133,-0.264],[0,0],[-0.514,5.137],[-8.231,0],[0,0],[0,0],[-0.053,0.293],[2.318,4.479]],"v":[[-0.022,6.868],[16.389,-0.936],[16.5,-1.793],[15.56,-6.868],[-0.022,2.338],[-15.594,-6.75],[-15.634,-6.524],[-16.5,-1.702],[-16.381,-0.839]],"c":true},"ix":2},"nm":"Path 1","mn":"ADBE Vector Shape - Group","hd":false},{"ty":"fl","c":{"a":0,"k":[0.325490196078,0.250980392157,0.203921583587,1],"ix":4},"o":{"a":0,"k":100,"ix":5},"r":1,"bm":0,"nm":"Fill 1","mn":"ADBE Vector Graphic - Fill","hd":false},{"ty":"tr","p":{"a":0,"k":[27.174,18.015],"ix":2},"a":{"a":0,"k":[0,0],"ix":1},"s":{"a":0,"k":[100,100],"ix":3},"r":{"a":0,"k":0,"ix":6},"o":{"a":0,"k":100,"ix":7},"sk":{"a":0,"k":0,"ix":4},"sa":{"a":0,"k":0,"ix":5},"nm":"Transform"}],"nm":"Group 2","np":2,"cix":2,"bm":0,"ix":2,"mn":"ADBE Vector Group","hd":false},{"ty":"gr","it":[{"ind":0,"ty":"sh","ix":1,"ks":{"a":0,"k":{"i":[[0.08,0.47],[0,0],[0,0],[9.88,1.27],[0.33,0.03],[0.39,0.03],[0.46,0.02],[0.42,0],[0.42,-0.01],[1.92,-6.96],[0,0],[0,-0.24],[-13.31,0],[0,8.5]],"o":[[0,0],[0,0],[-1.5,-6.41],[-0.33,-0.04],[-0.38,-0.04],[-0.46,-0.03],[-0.42,-0.01],[-0.43,0],[-11.29,0.38],[0,0],[-0.02,0.23],[0,8.5],[13.32,0],[0,-0.48]],"v":[[24,-1.42],[23.85,-2.27],[23.84,-2.3],[4.76,-15.09],[3.77,-15.2],[2.62,-15.3],[1.25,-15.37],[0,-15.39],[-1.27,-15.37],[-23.73,-2.7],[-24.08,-0.7],[-24.11,0],[0,15.39],[24.11,0]],"c":true},"ix":2},"nm":"Path 1","mn":"ADBE Vector Shape - Group","hd":false},{"ty":"fl","c":{"a":0,"k":[0.423529441684,0.321568627451,0.258823529412,1],"ix":4},"o":{"a":0,"k":100,"ix":5},"r":1,"bm":0,"nm":"Fill 1","mn":"ADBE Vector Graphic - Fill","hd":false},{"ty":"tr","p":{"a":0,"k":[27.14,15.64],"ix":2},"a":{"a":0,"k":[0,0],"ix":1},"s":{"a":0,"k":[100,100],"ix":3},"r":{"a":0,"k":0,"ix":6},"o":{"a":0,"k":100,"ix":7},"sk":{"a":0,"k":0,"ix":4},"sa":{"a":0,"k":0,"ix":5},"nm":"Transform"}],"nm":"Group 3","np":2,"cix":2,"bm":0,"ix":3,"mn":"ADBE Vector Group","hd":false},{"ty":"gr","it":[{"ind":0,"ty":"sh","ix":1,"ks":{"a":0,"k":{"i":[[0.04,-0.68],[0,0]],"o":[[0,0],[-0.19,0.65]],"v":[[-0.175,1],[0.175,-1]],"c":true},"ix":2},"nm":"Path 1","mn":"ADBE Vector Shape - Group","hd":false},{"ty":"fl","c":{"a":0,"k":[0.423529441684,0.321568627451,0.258823529412,1],"ix":4},"o":{"a":0,"k":100,"ix":5},"r":1,"bm":0,"nm":"Fill 1","mn":"ADBE Vector Graphic - Fill","hd":false},{"ty":"tr","p":{"a":0,"k":[3.235,13.94],"ix":2},"a":{"a":0,"k":[0,0],"ix":1},"s":{"a":0,"k":[100,100],"ix":3},"r":{"a":0,"k":0,"ix":6},"o":{"a":0,"k":100,"ix":7},"sk":{"a":0,"k":0,"ix":4},"sa":{"a":0,"k":0,"ix":5},"nm":"Transform"}],"nm":"Group 4","np":2,"cix":2,"bm":0,"ix":4,"mn":"ADBE Vector Group","hd":false},{"ty":"gr","it":[{"ind":0,"ty":"sh","ix":1,"ks":{"a":0,"k":{"i":[[0.083,0.454],[0,0],[0,-0.48],[13.32,0],[0,8.5],[-0.02,0.23],[0,0],[-0.211,-0.415],[-11.713,0],[-3.51,7.099]],"o":[[0,0],[0.08,0.47],[0,8.5],[-13.31,0],[0,-0.24],[0,0],[-0.081,0.459],[3.576,7.017],[11.797,0],[0.205,-0.414]],"v":[[25.448,-2.719],[23.965,-10.85],[24.075,-9.43],[-0.035,5.96],[-24.145,-9.43],[-24.115,-10.13],[-25.45,-2.577],[-25.266,-1.224],[-0.035,10.85],[25.277,-1.377]],"c":true},"ix":2},"nm":"Path 1","mn":"ADBE Vector Shape - Group","hd":false},{"ty":"fl","c":{"a":0,"k":[0.325490196078,0.250980392157,0.203921583587,1],"ix":4},"o":{"a":0,"k":100,"ix":5},"r":1,"bm":0,"nm":"Fill 1","mn":"ADBE Vector Graphic - Fill","hd":false},{"ty":"tr","p":{"a":0,"k":[27.175,25.07],"ix":2},"a":{"a":0,"k":[0,0],"ix":1},"s":{"a":0,"k":[100,100],"ix":3},"r":{"a":0,"k":0,"ix":6},"o":{"a":0,"k":100,"ix":7},"sk":{"a":0,"k":0,"ix":4},"sa":{"a":0,"k":0,"ix":5},"nm":"Transform"}],"nm":"Group 5","np":2,"cix":2,"bm":0,"ix":5,"mn":"ADBE Vector Group","hd":false},{"ty":"gr","it":[{"ind":0,"ty":"sh","ix":1,"ks":{"a":0,"k":{"i":[[0,0],[0.65,0.44],[0.48,0],[16.67,0],[0.8,0],[0.43,-0.27],[0.05,-0.76],[0,0],[0,0],[0,0],[0,0],[0,0],[-0.92,1.091],[0,0]],"o":[[-0.06,-0.73],[-0.43,-0.29],[-0.8,0],[-16.6,0],[-0.47,0],[-0.68,0.45],[0,0],[0,0],[0,0],[0,0],[0,0],[1.538,0],[0,0],[0,0]],"v":[[26.87,-3.595],[25.79,-5.465],[24.39,-5.895],[-0.04,3.085],[-24.39,-5.915],[-25.77,-5.505],[-26.88,-3.565],[-26.89,-3.565],[-26.89,5.915],[-24.39,5.915],[19.526,5.915],[23.072,5.915],[26.89,4.116],[26.89,-3.605]],"c":true},"ix":2},"nm":"Path 1","mn":"ADBE Vector Shape - Group","hd":false},{"ty":"fl","c":{"a":0,"k":[0.423529441684,0.321568627451,0.258823529412,1],"ix":4},"o":{"a":0,"k":100,"ix":5},"r":1,"bm":0,"nm":"Fill 1","mn":"ADBE Vector Graphic - Fill","hd":false},{"ty":"tr","p":{"a":0,"k":[27.14,43.551],"ix":2},"a":{"a":0,"k":[0,0],"ix":1},"s":{"a":0,"k":[100,100],"ix":3},"r":{"a":0,"k":0,"ix":6},"o":{"a":0,"k":100,"ix":7},"sk":{"a":0,"k":0,"ix":4},"sa":{"a":0,"k":0,"ix":5},"nm":"Transform"}],"nm":"Group 6","np":2,"cix":2,"bm":0,"ix":6,"mn":"ADBE Vector Group","hd":false},{"ty":"gr","it":[{"ind":0,"ty":"sh","ix":1,"ks":{"a":0,"k":{"i":[[-0.796,0.001],[0,0],[0,0],[0,0],[-16.604,0]],"o":[[0,0],[0,0],[0,0],[0.805,0.001],[16.666,0]],"v":[[24.391,4.432],[24.391,-13.417],[-24.391,-13.417],[-24.391,4.417],[-0.035,13.417]],"c":true},"ix":2},"nm":"Path 1","mn":"ADBE Vector Shape - Group","hd":false},{"ty":"fl","c":{"a":0,"k":[1,0.89019613827,0.666666666667,1],"ix":4},"o":{"a":0,"k":100,"ix":5},"r":1,"bm":0,"nm":"Fill 1","mn":"ADBE Vector Graphic - Fill","hd":false},{"ty":"tr","p":{"a":0,"k":[27.175,33.222],"ix":2},"a":{"a":0,"k":[0,0],"ix":1},"s":{"a":0,"k":[100,100],"ix":3},"r":{"a":0,"k":0,"ix":6},"o":{"a":0,"k":100,"ix":7},"sk":{"a":0,"k":0,"ix":4},"sa":{"a":0,"k":0,"ix":5},"nm":"Transform"}],"nm":"Group 7","np":2,"cix":2,"bm":0,"ix":7,"mn":"ADBE Vector Group","hd":false}],"ip":0,"op":60,"st":0,"bm":0},{"ddd":0,"ind":7,"ty":4,"nm":"Cup_01","parent":4,"sr":1,"ks":{"o":{"a":0,"k":100,"ix":11},"r":{"a":0,"k":0,"ix":10},"p":{"a":0,"k":[10.463,81.699,0],"ix":2},"a":{"a":0,"k":[27.14,24.858,0],"ix":1},"s":{"a":0,"k":[100,100,100],"ix":6}},"ao":0,"shapes":[{"ty":"gr","it":[{"ind":0,"ty":"sh","ix":1,"ks":{"a":0,"k":{"i":[[0.89,0],[0,0],[0,0.89],[0,0],[-0.89,0],[0,-0.889],[0,0]],"o":[[0,0],[-0.89,0],[0,0],[0,-0.889],[0.89,0],[0,0],[0,0.89]],"v":[[0,2.889],[0,2.889],[-1.611,1.278],[-1.611,-1.278],[0,-2.889],[1.611,-1.278],[1.611,1.278]],"c":true},"ix":2},"nm":"Path 1","mn":"ADBE Vector Shape - Group","hd":false},{"ty":"fl","c":{"a":0,"k":[0.325490196078,0.250980392157,0.203921583587,1],"ix":4},"o":{"a":0,"k":100,"ix":5},"r":1,"bm":0,"nm":"Fill 1","mn":"ADBE Vector Graphic - Fill","hd":false},{"ty":"tr","p":{"a":0,"k":[37.384,10.139],"ix":2},"a":{"a":0,"k":[0,0],"ix":1},"s":{"a":0,"k":[100,100],"ix":3},"r":{"a":0,"k":0,"ix":6},"o":{"a":0,"k":100,"ix":7},"sk":{"a":0,"k":0,"ix":4},"sa":{"a":0,"k":0,"ix":5},"nm":"Transform"}],"nm":"Group 1","np":2,"cix":2,"bm":0,"ix":1,"mn":"ADBE Vector Group","hd":false},{"ty":"gr","it":[{"ind":0,"ty":"sh","ix":1,"ks":{"a":0,"k":{"i":[[-7.594,0],[-2.276,4.531],[0.053,0.29],[0,0],[8.301,0],[0.605,5.081],[0,0],[0,0],[-0.137,-0.265]],"o":[[7.648,0],[0.133,-0.264],[0,0],[-0.514,5.137],[-8.231,0],[0,0],[0,0],[-0.053,0.293],[2.318,4.479]],"v":[[-0.022,6.868],[16.389,-0.936],[16.5,-1.793],[15.56,-6.868],[-0.022,2.338],[-15.594,-6.75],[-15.634,-6.524],[-16.5,-1.702],[-16.381,-0.839]],"c":true},"ix":2},"nm":"Path 1","mn":"ADBE Vector Shape - Group","hd":false},{"ty":"fl","c":{"a":0,"k":[0.325490196078,0.250980392157,0.203921583587,1],"ix":4},"o":{"a":0,"k":100,"ix":5},"r":1,"bm":0,"nm":"Fill 1","mn":"ADBE Vector Graphic - Fill","hd":false},{"ty":"tr","p":{"a":0,"k":[27.137,18.015],"ix":2},"a":{"a":0,"k":[0,0],"ix":1},"s":{"a":0,"k":[100,100],"ix":3},"r":{"a":0,"k":0,"ix":6},"o":{"a":0,"k":100,"ix":7},"sk":{"a":0,"k":0,"ix":4},"sa":{"a":0,"k":0,"ix":5},"nm":"Transform"}],"nm":"Group 2","np":2,"cix":2,"bm":0,"ix":2,"mn":"ADBE Vector Group","hd":false},{"ty":"gr","it":[{"ind":0,"ty":"sh","ix":1,"ks":{"a":0,"k":{"i":[[0.08,0.47],[0,0],[0,0],[9.88,1.27],[0.33,0.03],[0.39,0.03],[0.46,0.02],[0.42,0],[0.42,-0.01],[1.92,-6.96],[0,0],[0,-0.24],[-13.31,0],[0,8.5]],"o":[[0,0],[0,0],[-1.5,-6.41],[-0.33,-0.04],[-0.38,-0.04],[-0.46,-0.03],[-0.42,-0.01],[-0.43,0],[-11.29,0.38],[0,0],[-0.02,0.23],[0,8.5],[13.32,0],[0,-0.48]],"v":[[24,-1.42],[23.85,-2.27],[23.84,-2.3],[4.76,-15.09],[3.77,-15.2],[2.62,-15.3],[1.25,-15.37],[0,-15.39],[-1.27,-15.37],[-23.73,-2.7],[-24.08,-0.7],[-24.11,0],[0,15.39],[24.11,0]],"c":true},"ix":2},"nm":"Path 1","mn":"ADBE Vector Shape - Group","hd":false},{"ty":"fl","c":{"a":0,"k":[0.423529441684,0.321568627451,0.258823529412,1],"ix":4},"o":{"a":0,"k":100,"ix":5},"r":1,"bm":0,"nm":"Fill 1","mn":"ADBE Vector Graphic - Fill","hd":false},{"ty":"tr","p":{"a":0,"k":[27.102,15.64],"ix":2},"a":{"a":0,"k":[0,0],"ix":1},"s":{"a":0,"k":[100,100],"ix":3},"r":{"a":0,"k":0,"ix":6},"o":{"a":0,"k":100,"ix":7},"sk":{"a":0,"k":0,"ix":4},"sa":{"a":0,"k":0,"ix":5},"nm":"Transform"}],"nm":"Group 3","np":2,"cix":2,"bm":0,"ix":3,"mn":"ADBE Vector Group","hd":false},{"ty":"gr","it":[{"ind":0,"ty":"sh","ix":1,"ks":{"a":0,"k":{"i":[[0.04,-0.68],[0,0]],"o":[[0,0],[-0.19,0.65]],"v":[[-0.175,1],[0.175,-1]],"c":true},"ix":2},"nm":"Path 1","mn":"ADBE Vector Shape - Group","hd":false},{"ty":"fl","c":{"a":0,"k":[0.423529441684,0.321568627451,0.258823529412,1],"ix":4},"o":{"a":0,"k":100,"ix":5},"r":1,"bm":0,"nm":"Fill 1","mn":"ADBE Vector Graphic - Fill","hd":false},{"ty":"tr","p":{"a":0,"k":[3.198,13.94],"ix":2},"a":{"a":0,"k":[0,0],"ix":1},"s":{"a":0,"k":[100,100],"ix":3},"r":{"a":0,"k":0,"ix":6},"o":{"a":0,"k":100,"ix":7},"sk":{"a":0,"k":0,"ix":4},"sa":{"a":0,"k":0,"ix":5},"nm":"Transform"}],"nm":"Group 4","np":2,"cix":2,"bm":0,"ix":4,"mn":"ADBE Vector Group","hd":false},{"ty":"gr","it":[{"ind":0,"ty":"sh","ix":1,"ks":{"a":0,"k":{"i":[[0.083,0.454],[0,0],[0,-0.48],[13.32,0],[0,8.5],[-0.02,0.23],[0,0],[-0.211,-0.415],[-11.713,0],[-3.51,7.099]],"o":[[0,0],[0.08,0.47],[0,8.5],[-13.31,0],[0,-0.24],[0,0],[-0.081,0.459],[3.576,7.017],[11.797,0],[0.205,-0.414]],"v":[[25.448,-2.719],[23.965,-10.85],[24.075,-9.43],[-0.035,5.96],[-24.145,-9.43],[-24.115,-10.13],[-25.45,-2.577],[-25.266,-1.224],[-0.035,10.85],[25.277,-1.377]],"c":true},"ix":2},"nm":"Path 1","mn":"ADBE Vector Shape - Group","hd":false},{"ty":"fl","c":{"a":0,"k":[0.325490196078,0.250980392157,0.203921583587,1],"ix":4},"o":{"a":0,"k":100,"ix":5},"r":1,"bm":0,"nm":"Fill 1","mn":"ADBE Vector Graphic - Fill","hd":false},{"ty":"tr","p":{"a":0,"k":[27.137,25.07],"ix":2},"a":{"a":0,"k":[0,0],"ix":1},"s":{"a":0,"k":[100,100],"ix":3},"r":{"a":0,"k":0,"ix":6},"o":{"a":0,"k":100,"ix":7},"sk":{"a":0,"k":0,"ix":4},"sa":{"a":0,"k":0,"ix":5},"nm":"Transform"}],"nm":"Group 5","np":2,"cix":2,"bm":0,"ix":5,"mn":"ADBE Vector Group","hd":false},{"ty":"gr","it":[{"ind":0,"ty":"sh","ix":1,"ks":{"a":0,"k":{"i":[[0,0],[0.65,0.44],[0.48,0],[16.67,0],[0.8,0],[0.43,-0.27],[0.04,-0.76],[0,0],[0,0],[-0.956,-0.168],[-0.297,0],[0,0],[0,0],[0,0],[0,0]],"o":[[-0.06,-0.73],[-0.43,-0.29],[-0.8,0],[-16.6,0],[-0.48,0],[-0.68,0.45],[0,0],[0,0],[0.688,0.627],[0.283,0.049],[0,0],[0,0],[0,0],[0,0],[0,0]],"v":[[26.87,-3.595],[25.79,-5.465],[24.39,-5.895],[-0.04,3.085],[-24.39,-5.915],[-25.77,-5.505],[-26.88,-3.565],[-26.89,-3.565],[-26.89,4.594],[-24.39,5.828],[-23.523,5.915],[-19.978,5.915],[24.39,5.915],[26.89,5.915],[26.89,-3.605]],"c":true},"ix":2},"nm":"Path 1","mn":"ADBE Vector Shape - Group","hd":false},{"ty":"fl","c":{"a":0,"k":[0.423529441684,0.321568627451,0.258823529412,1],"ix":4},"o":{"a":0,"k":100,"ix":5},"r":1,"bm":0,"nm":"Fill 1","mn":"ADBE Vector Graphic - Fill","hd":false},{"ty":"tr","p":{"a":0,"k":[27.14,43.551],"ix":2},"a":{"a":0,"k":[0,0],"ix":1},"s":{"a":0,"k":[100,100],"ix":3},"r":{"a":0,"k":0,"ix":6},"o":{"a":0,"k":100,"ix":7},"sk":{"a":0,"k":0,"ix":4},"sa":{"a":0,"k":0,"ix":5},"nm":"Transform"}],"nm":"Group 6","np":2,"cix":2,"bm":0,"ix":6,"mn":"ADBE Vector Group","hd":false},{"ty":"gr","it":[{"ind":0,"ty":"sh","ix":1,"ks":{"a":0,"k":{"i":[[-0.8,0],[0,0],[0,0],[0,0],[-16.6,0]],"o":[[0,0],[0,0],[0,0],[0.8,0],[16.67,0]],"v":[[24.39,4.435],[24.39,-13.415],[-24.39,-13.415],[-24.39,4.415],[-0.04,13.415]],"c":true},"ix":2},"nm":"Path 1","mn":"ADBE Vector Shape - Group","hd":false},{"ty":"fl","c":{"a":0,"k":[1,0.89019613827,0.666666666667,1],"ix":4},"o":{"a":0,"k":100,"ix":5},"r":1,"bm":0,"nm":"Fill 1","mn":"ADBE Vector Graphic - Fill","hd":false},{"ty":"tr","p":{"a":0,"k":[27.14,33.221],"ix":2},"a":{"a":0,"k":[0,0],"ix":1},"s":{"a":0,"k":[100,100],"ix":3},"r":{"a":0,"k":0,"ix":6},"o":{"a":0,"k":100,"ix":7},"sk":{"a":0,"k":0,"ix":4},"sa":{"a":0,"k":0,"ix":5},"nm":"Transform"}],"nm":"Group 7","np":2,"cix":2,"bm":0,"ix":7,"mn":"ADBE Vector Group","hd":false}],"ip":0,"op":60,"st":0,"bm":0},{"ddd":0,"ind":8,"ty":4,"nm":"Cup_04","parent":4,"sr":1,"ks":{"o":{"a":0,"k":100,"ix":11},"r":{"a":0,"k":0,"ix":10},"p":{"a":0,"k":[88.891,42.932,0],"ix":2},"a":{"a":0,"k":[23.648,22.265,0],"ix":1},"s":{"a":0,"k":[100,100,100],"ix":6}},"ao":0,"shapes":[{"ty":"gr","it":[{"ind":0,"ty":"sh","ix":1,"ks":{"a":0,"k":{"i":[[0.691,0],[0,0],[0,0.691],[-0.691,0],[0,0],[0,-0.691]],"o":[[0,0],[-0.691,0],[0,-0.691],[0,0],[0.691,0],[0,0.691]],"v":[[0.616,1.257],[-0.615,1.257],[-1.872,0.001],[-0.615,-1.257],[0.616,-1.257],[1.872,0.001]],"c":true},"ix":2},"nm":"Path 1","mn":"ADBE Vector Shape - Group","hd":false},{"ty":"fl","c":{"a":0,"k":[0.439215716194,0.345098039216,0.282352941176,1],"ix":4},"o":{"a":0,"k":100,"ix":5},"r":1,"bm":0,"nm":"Fill 1","mn":"ADBE Vector Graphic - Fill","hd":false},{"ty":"tr","p":{"a":0,"k":[39.43,21.129],"ix":2},"a":{"a":0,"k":[0,0],"ix":1},"s":{"a":0,"k":[100,100],"ix":3},"r":{"a":0,"k":0,"ix":6},"o":{"a":0,"k":100,"ix":7},"sk":{"a":0,"k":0,"ix":4},"sa":{"a":0,"k":0,"ix":5},"nm":"Transform"}],"nm":"Group 1","np":2,"cix":2,"bm":0,"ix":1,"mn":"ADBE Vector Group","hd":false},{"ty":"gr","it":[{"ind":0,"ty":"sh","ix":1,"ks":{"a":0,"k":{"i":[[0.349,0.117],[0,0],[-0.117,0.349],[0,0],[-0.349,-0.117],[0,0],[0.118,-0.349],[0,0]],"o":[[0,0],[-0.349,-0.118],[0,0],[0.118,-0.349],[0,0],[0.348,0.117],[0,0],[-0.117,0.349]],"v":[[-0.347,1.417],[-0.58,1.339],[-1.001,0.491],[-0.501,-0.995],[0.347,-1.417],[0.58,-1.338],[1,-0.491],[0.5,0.996]],"c":true},"ix":2},"nm":"Path 1","mn":"ADBE Vector Shape - Group","hd":false},{"ty":"fl","c":{"a":0,"k":[0.439215716194,0.345098039216,0.282352941176,1],"ix":4},"o":{"a":0,"k":100,"ix":5},"r":1,"bm":0,"nm":"Fill 1","mn":"ADBE Vector Graphic - Fill","hd":false},{"ty":"tr","p":{"a":0,"k":[6.584,22.987],"ix":2},"a":{"a":0,"k":[0,0],"ix":1},"s":{"a":0,"k":[100,100],"ix":3},"r":{"a":0,"k":0,"ix":6},"o":{"a":0,"k":100,"ix":7},"sk":{"a":0,"k":0,"ix":4},"sa":{"a":0,"k":0,"ix":5},"nm":"Transform"}],"nm":"Group 2","np":2,"cix":2,"bm":0,"ix":2,"mn":"ADBE Vector Group","hd":false},{"ty":"gr","it":[{"ind":0,"ty":"sh","ix":1,"ks":{"a":0,"k":{"i":[[0.551,0],[0,0],[0,0.551],[-0.551,0],[0,0],[0,-0.55]],"o":[[0,0],[-0.551,0],[0,-0.55],[0,0],[0.551,0],[0,0.551]],"v":[[0.69,1.001],[-0.69,1.001],[-1.692,-0.001],[-0.69,-1.001],[0.69,-1.001],[1.692,-0.001]],"c":true},"ix":2},"nm":"Path 1","mn":"ADBE Vector Shape - Group","hd":false},{"ty":"fl","c":{"a":0,"k":[0.439215716194,0.345098039216,0.282352941176,1],"ix":4},"o":{"a":0,"k":100,"ix":5},"r":1,"bm":0,"nm":"Fill 1","mn":"ADBE Vector Graphic - Fill","hd":false},{"ty":"tr","p":{"a":0,"k":[15.802,13.106],"ix":2},"a":{"a":0,"k":[0,0],"ix":1},"s":{"a":0,"k":[100,100],"ix":3},"r":{"a":0,"k":0,"ix":6},"o":{"a":0,"k":100,"ix":7},"sk":{"a":0,"k":0,"ix":4},"sa":{"a":0,"k":0,"ix":5},"nm":"Transform"}],"nm":"Group 3","np":2,"cix":2,"bm":0,"ix":3,"mn":"ADBE Vector Group","hd":false},{"ty":"gr","it":[{"ind":0,"ty":"sh","ix":1,"ks":{"a":0,"k":{"i":[[0.59,0],[0,0],[0,0.59],[-0.59,0],[0,-0.59]],"o":[[0,0],[-0.59,0],[0,-0.59],[0.59,0],[0,0.59]],"v":[[0,1.073],[0,1.073],[-1.073,0],[0,-1.073],[1.073,0]],"c":true},"ix":2},"nm":"Path 1","mn":"ADBE Vector Shape - Group","hd":false},{"ty":"fl","c":{"a":0,"k":[0.439215716194,0.345098039216,0.282352941176,1],"ix":4},"o":{"a":0,"k":100,"ix":5},"r":1,"bm":0,"nm":"Fill 1","mn":"ADBE Vector Graphic - Fill","hd":false},{"ty":"tr","p":{"a":0,"k":[24.928,28.713],"ix":2},"a":{"a":0,"k":[0,0],"ix":1},"s":{"a":0,"k":[100,100],"ix":3},"r":{"a":0,"k":0,"ix":6},"o":{"a":0,"k":100,"ix":7},"sk":{"a":0,"k":0,"ix":4},"sa":{"a":0,"k":0,"ix":5},"nm":"Transform"}],"nm":"Group 4","np":2,"cix":2,"bm":0,"ix":4,"mn":"ADBE Vector Group","hd":false},{"ty":"gr","it":[{"ind":0,"ty":"sh","ix":1,"ks":{"a":0,"k":{"i":[[-0.253,-0.221],[0,0],[-0.221,0.252],[0,0],[0.253,0.221],[0,0],[0.221,-0.253],[0,0]],"o":[[0,0],[0.253,0.221],[0,0],[0.222,-0.253],[0,0],[-0.253,-0.221],[0,0],[-0.222,0.253]],"v":[[-1.626,-0.275],[0.488,1.575],[1.35,1.518],[1.683,1.137],[1.626,0.275],[-0.488,-1.575],[-1.35,-1.518],[-1.683,-1.137]],"c":true},"ix":2},"nm":"Path 1","mn":"ADBE Vector Shape - Group","hd":false},{"ty":"fl","c":{"a":0,"k":[0.439215716194,0.345098039216,0.282352941176,1],"ix":4},"o":{"a":0,"k":100,"ix":5},"r":1,"bm":0,"nm":"Fill 1","mn":"ADBE Vector Graphic - Fill","hd":false},{"ty":"tr","p":{"a":0,"k":[31.152,23.326],"ix":2},"a":{"a":0,"k":[0,0],"ix":1},"s":{"a":0,"k":[100,100],"ix":3},"r":{"a":0,"k":0,"ix":6},"o":{"a":0,"k":100,"ix":7},"sk":{"a":0,"k":0,"ix":4},"sa":{"a":0,"k":0,"ix":5},"nm":"Transform"}],"nm":"Group 5","np":2,"cix":2,"bm":0,"ix":5,"mn":"ADBE Vector Group","hd":false},{"ty":"gr","it":[{"ind":0,"ty":"sh","ix":1,"ks":{"a":0,"k":{"i":[[0.337,0.194],[0,0],[-0.194,0.336],[0,0],[-0.336,-0.195],[0.194,-0.337],[0,0]],"o":[[0,0],[-0.337,-0.194],[0,0],[0.194,-0.336],[0.337,0.194],[0,0],[-0.194,0.337]],"v":[[-0.849,1.472],[-0.849,1.472],[-1.109,0.507],[-0.116,-1.213],[0.849,-1.471],[1.108,-0.506],[0.115,1.213]],"c":true},"ix":2},"nm":"Path 1","mn":"ADBE Vector Shape - Group","hd":false},{"ty":"fl","c":{"a":0,"k":[0.439215716194,0.345098039216,0.282352941176,1],"ix":4},"o":{"a":0,"k":100,"ix":5},"r":1,"bm":0,"nm":"Fill 1","mn":"ADBE Vector Graphic - Fill","hd":false},{"ty":"tr","p":{"a":0,"k":[26.422,15.747],"ix":2},"a":{"a":0,"k":[0,0],"ix":1},"s":{"a":0,"k":[100,100],"ix":3},"r":{"a":0,"k":0,"ix":6},"o":{"a":0,"k":100,"ix":7},"sk":{"a":0,"k":0,"ix":4},"sa":{"a":0,"k":0,"ix":5},"nm":"Transform"}],"nm":"Group 6","np":2,"cix":2,"bm":0,"ix":6,"mn":"ADBE Vector Group","hd":false},{"ty":"gr","it":[{"ind":0,"ty":"sh","ix":1,"ks":{"a":0,"k":{"i":[[0.564,-0.187],[0,0],[0.186,0.563],[-0.564,0.187],[0,0],[-0.187,-0.564]],"o":[[0,0],[-0.564,0.187],[-0.187,-0.564],[0,0],[0.564,-0.187],[0.186,0.563]],"v":[[1.023,0.799],[-0.344,1.251],[-1.708,0.566],[-1.022,-0.799],[0.344,-1.251],[1.709,-0.565]],"c":true},"ix":2},"nm":"Path 1","mn":"ADBE Vector Shape - Group","hd":false},{"ty":"fl","c":{"a":0,"k":[0.439215716194,0.345098039216,0.282352941176,1],"ix":4},"o":{"a":0,"k":100,"ix":5},"r":1,"bm":0,"nm":"Fill 1","mn":"ADBE Vector Graphic - Fill","hd":false},{"ty":"tr","p":{"a":0,"k":[15.694,22.025],"ix":2},"a":{"a":0,"k":[0,0],"ix":1},"s":{"a":0,"k":[100,100],"ix":3},"r":{"a":0,"k":0,"ix":6},"o":{"a":0,"k":100,"ix":7},"sk":{"a":0,"k":0,"ix":4},"sa":{"a":0,"k":0,"ix":5},"nm":"Transform"}],"nm":"Group 7","np":2,"cix":2,"bm":0,"ix":7,"mn":"ADBE Vector Group","hd":false},{"ty":"gr","it":[{"ind":0,"ty":"sh","ix":1,"ks":{"a":0,"k":{"i":[[1.257,1.937],[-0.084,0.255],[-3.886,1.387],[-1.728,1.734],[-4.888,0.261],[0.613,0.525],[0.018,0.016],[-0.88,-0.132],[-0.267,-1.336],[-1.584,-2.303],[-6.939,-12.24],[0.095,-0.247],[17.022,-0.962]],"o":[[-0.146,-0.224],[1.154,-3.509],[4.031,-1.44],[1.522,-1.527],[0.807,-0.043],[-0.018,-0.016],[-0.682,-0.572],[2.557,0.384],[0.432,2.16],[1.569,2.282],[0.13,0.231],[-0.746,1.937],[-14.953,0.845]],"v":[[-22.383,3.819],[-22.473,3.058],[-17.159,-4.029],[-13.704,-8.486],[-3.203,-11.462],[-2.67,-13.032],[-2.724,-13.079],[-2.025,-14.637],[2.996,-11.084],[8.323,-7.629],[22.399,1.924],[22.462,2.682],[0.508,13.924]],"c":true},"ix":2},"nm":"Path 1","mn":"ADBE Vector Shape - Group","hd":false},{"ty":"fl","c":{"a":0,"k":[0.964705942191,0.847058883368,0.701960784314,1],"ix":4},"o":{"a":0,"k":100,"ix":5},"r":1,"bm":0,"nm":"Fill 1","mn":"ADBE Vector Graphic - Fill","hd":false},{"ty":"tr","p":{"a":0,"k":[23.855,19.864],"ix":2},"a":{"a":0,"k":[0,0],"ix":1},"s":{"a":0,"k":[100,100],"ix":3},"r":{"a":0,"k":0,"ix":6},"o":{"a":0,"k":100,"ix":7},"sk":{"a":0,"k":0,"ix":4},"sa":{"a":0,"k":0,"ix":5},"nm":"Transform"}],"nm":"Group 8","np":2,"cix":2,"bm":0,"ix":8,"mn":"ADBE Vector Group","hd":false},{"ty":"gr","it":[{"ind":0,"ty":"sh","ix":1,"ks":{"a":0,"k":{"i":[[-12.606,0],[-0.945,7.707],[0,0],[0,0],[0,0],[9.601,1.234],[0.32,0.029],[0.379,0.029],[0.447,0.019],[0.408,0],[0.408,-0.01],[1.865,-6.764],[0.053,-0.241],[0,0],[0,0]],"o":[[12.32,0],[0,0],[0,0],[0,0],[-1.457,-6.229],[-0.321,-0.039],[-0.37,-0.039],[-0.447,-0.029],[-0.408,-0.01],[-0.418,0],[-10.972,0.369],[-0.025,0.245],[0,0],[0,0],[0.514,7.97]],"v":[[0.028,16.899],[23.378,3.125],[23.351,0.563],[23.204,-0.263],[23.195,-0.292],[4.654,-16.608],[3.691,-16.715],[2.573,-16.812],[1.242,-16.88],[0.028,-16.899],[-1.206,-16.88],[-23.033,-0.68],[-23.161,0.047],[-23.372,1.263],[-23.378,2.568]],"c":true},"ix":2},"nm":"Path 1","mn":"ADBE Vector Shape - Group","hd":false},{"ty":"fl","c":{"a":0,"k":[0.894117706897,0.964705942191,0.976470648074,1],"ix":4},"o":{"a":0,"k":100,"ix":5},"r":1,"bm":0,"nm":"Fill 1","mn":"ADBE Vector Graphic - Fill","hd":false},{"ty":"tr","p":{"a":0,"k":[23.577,16.899],"ix":2},"a":{"a":0,"k":[0,0],"ix":1},"s":{"a":0,"k":[100,100],"ix":3},"r":{"a":0,"k":0,"ix":6},"o":{"a":0,"k":100,"ix":7},"sk":{"a":0,"k":0,"ix":4},"sa":{"a":0,"k":0,"ix":5},"nm":"Transform"}],"nm":"Group 9","np":2,"cix":2,"bm":0,"ix":9,"mn":"ADBE Vector Group","hd":false},{"ty":"gr","it":[{"ind":0,"ty":"sh","ix":1,"ks":{"a":0,"k":{"i":[[12.32,0],[0.514,7.97],[0,0],[-11.729,0],[-3.12,7.221],[0,0]],"o":[[-12.606,0],[0,0],[3.188,7.143],[11.807,0],[0,0],[-0.945,7.707]],"v":[[0,4.79],[-23.405,-9.541],[-23.43,-2.266],[0,9.542],[23.43,-1.51],[23.35,-8.984]],"c":true},"ix":2},"nm":"Path 1","mn":"ADBE Vector Shape - Group","hd":false},{"ty":"fl","c":{"a":0,"k":[1,1,1,1],"ix":4},"o":{"a":0,"k":100,"ix":5},"r":1,"bm":0,"nm":"Fill 1","mn":"ADBE Vector Graphic - Fill","hd":false},{"ty":"tr","p":{"a":0,"k":[23.605,29.009],"ix":2},"a":{"a":0,"k":[0,0],"ix":1},"s":{"a":0,"k":[100,100],"ix":3},"r":{"a":0,"k":0,"ix":6},"o":{"a":0,"k":100,"ix":7},"sk":{"a":0,"k":0,"ix":4},"sa":{"a":0,"k":0,"ix":5},"nm":"Transform"}],"nm":"Group 10","np":2,"cix":2,"bm":0,"ix":10,"mn":"ADBE Vector Group","hd":false},{"ty":"gr","it":[{"ind":0,"ty":"sh","ix":1,"ks":{"a":0,"k":{"i":[[0,0],[0,0],[0,0],[0.01,0.02],[20.07,0.61],[0.01,-0.11],[0,0],[0,0],[0,0],[0,0],[0,0],[0,0],[0.01,0.01],[0,0],[-0.06,0.28],[0,0],[-19.31,-0.58],[-1.21,-3.11],[-0.07,-0.23],[-0.01,-0.06],[0,0],[0,0]],"o":[[0,0],[0,0],[0,0],[-0.12,-0.65],[-20.65,-0.62],[0,0],[0,0],[0,0],[0,0],[0,0],[0,0],[0,0],[0,0],[0.01,-0.06],[0,0],[0.53,-2.36],[17.04,0.51],[0.14,0.34],[0.09,0.35],[0,0],[0,0],[0,0]],"v":[[22.465,17.095],[22.465,1.785],[22.465,-4.475],[22.455,-4.505],[0.085,-15.545],[-22.135,-4.965],[-22.155,-3.585],[-22.235,1.615],[-22.465,17.095],[-22.945,17.095],[-23.435,17.095],[-23.185,-0.005],[-23.185,-0.015],[-23.105,-5.025],[-23.015,-5.545],[-23.015,-5.555],[0.115,-16.515],[22.995,-6.035],[23.295,-5.165],[23.425,-4.535],[23.435,17.095],[22.945,17.095]],"c":true},"ix":2},"nm":"Path 1","mn":"ADBE Vector Shape - Group","hd":false},{"ty":"fl","c":{"a":0,"k":[1,1,1,1],"ix":4},"o":{"a":0,"k":100,"ix":5},"r":1,"bm":0,"nm":"Fill 1","mn":"ADBE Vector Graphic - Fill","hd":false},{"ty":"tr","p":{"a":0,"k":[23.685,27.435],"ix":2},"a":{"a":0,"k":[0,0],"ix":1},"s":{"a":0,"k":[100,100],"ix":3},"r":{"a":0,"k":0,"ix":6},"o":{"a":0,"k":100,"ix":7},"sk":{"a":0,"k":0,"ix":4},"sa":{"a":0,"k":0,"ix":5},"nm":"Transform"}],"nm":"Group 11","np":2,"cix":2,"bm":0,"ix":11,"mn":"ADBE Vector Group","hd":false},{"ty":"gr","it":[{"ind":0,"ty":"sh","ix":1,"ks":{"a":0,"k":{"i":[[0,0],[0,0],[0,0],[0,0],[0,0],[0,0],[-0.01,0.01],[0,0],[-21.45,-0.64],[-0.79,-2.49],[0,0],[0,0],[0,0]],"o":[[0,0],[0,0],[0,0],[0,0],[0,0],[0,0],[0,0],[0,0],[17.98,0.54],[0.15,0.48],[0,0],[0,0],[0,0]],"v":[[22.465,16.885],[-22.465,16.885],[-22.945,16.885],[-22.705,0.655],[-22.705,0.645],[-22.625,-4.735],[-22.625,-4.745],[-22.615,-5.225],[0.095,-16.245],[22.755,-5.455],[22.945,-4.685],[22.945,0.695],[22.945,16.885]],"c":true},"ix":2},"nm":"Path 1","mn":"ADBE Vector Shape - Group","hd":false},{"ty":"fl","c":{"a":0,"k":[0.662745098039,0.454901990704,0.313725490196,1],"ix":4},"o":{"a":0,"k":100,"ix":5},"r":1,"bm":0,"nm":"Fill 1","mn":"ADBE Vector Graphic - Fill","hd":false},{"ty":"tr","p":{"a":0,"k":[23.685,27.645],"ix":2},"a":{"a":0,"k":[0,0],"ix":1},"s":{"a":0,"k":[100,100],"ix":3},"r":{"a":0,"k":0,"ix":6},"o":{"a":0,"k":100,"ix":7},"sk":{"a":0,"k":0,"ix":4},"sa":{"a":0,"k":0,"ix":5},"nm":"Transform"}],"nm":"Group 12","np":2,"cix":2,"bm":0,"ix":12,"mn":"ADBE Vector Group","hd":false}],"ip":0,"op":60,"st":0,"bm":0},{"ddd":0,"ind":9,"ty":4,"nm":"Cup_03","parent":4,"sr":1,"ks":{"o":{"a":0,"k":100,"ix":11},"r":{"a":0,"k":0,"ix":10},"p":{"a":0,"k":[10.504,43.684,0],"ix":2},"a":{"a":0,"k":[23.451,21.513,0],"ix":1},"s":{"a":0,"k":[100,100,100],"ix":6}},"ao":0,"shapes":[{"ty":"gr","it":[{"ind":0,"ty":"sh","ix":1,"ks":{"a":0,"k":{"i":[[0,0],[0,0]],"o":[[1.5,1.178],[0,0]],"v":[[-1.714,-0.589],[1.714,-0.107]],"c":false},"ix":2},"nm":"Path 1","mn":"ADBE Vector Shape - Group","hd":false},{"ty":"st","c":{"a":0,"k":[0.937254961799,0.878431432387,0.733333333333,1],"ix":3},"o":{"a":0,"k":100,"ix":4},"w":{"a":0,"k":0.964,"ix":5},"lc":2,"lj":1,"ml":10,"bm":0,"nm":"Stroke 1","mn":"ADBE Vector Graphic - Stroke","hd":false},{"ty":"tr","p":{"a":0,"k":[22.392,10.187],"ix":2},"a":{"a":0,"k":[0,0],"ix":1},"s":{"a":0,"k":[100,100],"ix":3},"r":{"a":0,"k":0,"ix":6},"o":{"a":0,"k":100,"ix":7},"sk":{"a":0,"k":0,"ix":4},"sa":{"a":0,"k":0,"ix":5},"nm":"Transform"}],"nm":"Group 1","np":2,"cix":2,"bm":0,"ix":1,"mn":"ADBE Vector Group","hd":false},{"ty":"gr","it":[{"ind":0,"ty":"sh","ix":1,"ks":{"a":0,"k":{"i":[[0,0],[10.606,1.714]],"o":[[-4.52,2.817],[0,0]],"v":[[12.062,-3.016],[-12.062,1.301]],"c":false},"ix":2},"nm":"Path 1","mn":"ADBE Vector Shape - Group","hd":false},{"ty":"st","c":{"a":0,"k":[0.937254961799,0.878431432387,0.733333333333,1],"ix":3},"o":{"a":0,"k":100,"ix":4},"w":{"a":0,"k":0.964,"ix":5},"lc":2,"lj":1,"ml":10,"bm":0,"nm":"Stroke 1","mn":"ADBE Vector Graphic - Stroke","hd":false},{"ty":"tr","p":{"a":0,"k":[27.277,22.331],"ix":2},"a":{"a":0,"k":[0,0],"ix":1},"s":{"a":0,"k":[100,100],"ix":3},"r":{"a":0,"k":0,"ix":6},"o":{"a":0,"k":100,"ix":7},"sk":{"a":0,"k":0,"ix":4},"sa":{"a":0,"k":0,"ix":5},"nm":"Transform"}],"nm":"Group 2","np":2,"cix":2,"bm":0,"ix":2,"mn":"ADBE Vector Group","hd":false},{"ty":"gr","it":[{"ind":0,"ty":"sh","ix":1,"ks":{"a":0,"k":{"i":[[0,0],[-6.856,2.464]],"o":[[0,0],[0,0]],"v":[[-7.124,-1.588],[7.124,-0.876]],"c":false},"ix":2},"nm":"Path 1","mn":"ADBE Vector Shape - Group","hd":false},{"ty":"st","c":{"a":0,"k":[0.937254961799,0.878431432387,0.733333333333,1],"ix":3},"o":{"a":0,"k":100,"ix":4},"w":{"a":0,"k":0.964,"ix":5},"lc":2,"lj":1,"ml":10,"bm":0,"nm":"Stroke 1","mn":"ADBE Vector Graphic - Stroke","hd":false},{"ty":"tr","p":{"a":0,"k":[16.982,17.117],"ix":2},"a":{"a":0,"k":[0,0],"ix":1},"s":{"a":0,"k":[100,100],"ix":3},"r":{"a":0,"k":0,"ix":6},"o":{"a":0,"k":100,"ix":7},"sk":{"a":0,"k":0,"ix":4},"sa":{"a":0,"k":0,"ix":5},"nm":"Transform"}],"nm":"Group 3","np":2,"cix":2,"bm":0,"ix":3,"mn":"ADBE Vector Group","hd":false},{"ty":"gr","it":[{"ind":0,"ty":"sh","ix":1,"ks":{"a":0,"k":{"i":[[1.247,1.921],[-0.083,0.253],[-3.856,1.377],[-1.714,1.721],[-4.85,0.26],[0.608,0.521],[0.018,0.015],[-0.873,-0.131],[-0.265,-1.326],[-1.571,-2.286],[-6.885,-12.145],[0.094,-0.246],[16.889,-0.954]],"o":[[-0.145,-0.223],[1.145,-3.482],[4,-1.429],[1.51,-1.515],[0.8,-0.042],[-0.018,-0.016],[-0.676,-0.569],[2.537,0.382],[0.428,2.142],[1.556,2.264],[0.129,0.229],[-0.74,1.922],[-14.836,0.839]],"v":[[-22.208,3.789],[-22.297,3.034],[-17.025,-3.998],[-13.597,-8.42],[-3.178,-11.373],[-2.649,-12.93],[-2.703,-12.976],[-2.009,-14.523],[2.973,-10.997],[8.258,-7.569],[22.224,1.909],[22.286,2.661],[0.504,13.815]],"c":true},"ix":2},"nm":"Path 1","mn":"ADBE Vector Shape - Group","hd":false},{"ty":"fl","c":{"a":0,"k":[1,0.992156922583,0.921568687289,1],"ix":4},"o":{"a":0,"k":100,"ix":5},"r":1,"bm":0,"nm":"Fill 1","mn":"ADBE Vector Graphic - Fill","hd":false},{"ty":"tr","p":{"a":0,"k":[23.408,19.646],"ix":2},"a":{"a":0,"k":[0,0],"ix":1},"s":{"a":0,"k":[100,100],"ix":3},"r":{"a":0,"k":0,"ix":6},"o":{"a":0,"k":100,"ix":7},"sk":{"a":0,"k":0,"ix":4},"sa":{"a":0,"k":0,"ix":5},"nm":"Transform"}],"nm":"Group 4","np":2,"cix":2,"bm":0,"ix":4,"mn":"ADBE Vector Group","hd":false},{"ty":"gr","it":[{"ind":0,"ty":"sh","ix":1,"ks":{"a":0,"k":{"i":[[-12.508,0],[-0.937,7.647],[0,0],[0,0],[0,0],[9.526,1.225],[0.318,0.029],[0.376,0.028],[0.444,0.019],[0.405,0],[0.405,-0.01],[1.851,-6.711],[0.052,-0.239],[0,0],[0,0]],"o":[[12.224,0],[0,0],[0,0],[0,0],[-1.446,-6.181],[-0.319,-0.039],[-0.367,-0.039],[-0.443,-0.029],[-0.405,-0.01],[-0.415,0],[-10.885,0.366],[-0.024,0.243],[0,0],[0,0],[0.51,7.908]],"v":[[0.028,16.767],[23.195,3.101],[23.167,0.559],[23.023,-0.26],[23.013,-0.289],[4.617,-16.478],[3.662,-16.584],[2.553,-16.68],[1.232,-16.748],[0.028,-16.767],[-1.198,-16.748],[-22.852,-0.675],[-22.979,0.047],[-23.19,1.253],[-23.195,2.548]],"c":true},"ix":2},"nm":"Path 1","mn":"ADBE Vector Shape - Group","hd":false},{"ty":"fl","c":{"a":0,"k":[0.894117706897,0.964705942191,0.976470648074,1],"ix":4},"o":{"a":0,"k":100,"ix":5},"r":1,"bm":0,"nm":"Fill 1","mn":"ADBE Vector Graphic - Fill","hd":false},{"ty":"tr","p":{"a":0,"k":[23.38,16.767],"ix":2},"a":{"a":0,"k":[0,0],"ix":1},"s":{"a":0,"k":[100,100],"ix":3},"r":{"a":0,"k":0,"ix":6},"o":{"a":0,"k":100,"ix":7},"sk":{"a":0,"k":0,"ix":4},"sa":{"a":0,"k":0,"ix":5},"nm":"Transform"}],"nm":"Group 5","np":2,"cix":2,"bm":0,"ix":5,"mn":"ADBE Vector Group","hd":false},{"ty":"gr","it":[{"ind":0,"ty":"sh","ix":1,"ks":{"a":0,"k":{"i":[[12.224,0],[0.51,7.908],[0,0],[-11.638,0],[-3.095,7.164],[0,0]],"o":[[-12.508,0],[0,0],[3.163,7.086],[11.715,0],[0,0],[-0.937,7.647]],"v":[[0,4.752],[-23.222,-9.467],[-23.247,-2.248],[0,9.467],[23.246,-1.499],[23.167,-8.914]],"c":true},"ix":2},"nm":"Path 1","mn":"ADBE Vector Shape - Group","hd":false},{"ty":"fl","c":{"a":0,"k":[1,1,1,1],"ix":4},"o":{"a":0,"k":100,"ix":5},"r":1,"bm":0,"nm":"Fill 1","mn":"ADBE Vector Graphic - Fill","hd":false},{"ty":"tr","p":{"a":0,"k":[23.407,28.782],"ix":2},"a":{"a":0,"k":[0,0],"ix":1},"s":{"a":0,"k":[100,100],"ix":3},"r":{"a":0,"k":0,"ix":6},"o":{"a":0,"k":100,"ix":7},"sk":{"a":0,"k":0,"ix":4},"sa":{"a":0,"k":0,"ix":5},"nm":"Transform"}],"nm":"Group 6","np":2,"cix":2,"bm":0,"ix":6,"mn":"ADBE Vector Group","hd":false},{"ty":"gr","it":[{"ind":0,"ty":"sh","ix":1,"ks":{"a":0,"k":{"i":[[0,0],[0,0],[0,0],[0,0],[0.01,0.01],[20.13,0.61],[0.01,-0.11],[0,0],[0,0],[0,0],[0,0],[0,0],[0,0],[0,0],[0,0],[-0.06,0.28],[0,0],[-19.15,-0.56],[-1.2,-3.07],[-0.06,-0.23],[0,0],[-0.01,-0.06],[0,0]],"o":[[0,0],[0,0],[0,0],[0,0],[-0.08,-0.45],[-20.54,-0.62],[0,0],[0,0],[0,0],[0,0],[0,0],[0,0],[0,0],[0,0],[0.01,-0.06],[0,0],[0.53,-2.34],[16.92,0.51],[0.14,0.33],[0,0],[0.1,0.32],[0,0],[0,0]],"v":[[22.765,16.375],[22.275,16.375],[22.275,2.335],[22.275,-3.875],[22.265,-3.895],[0.075,-14.855],[-21.965,-4.355],[-21.985,-2.985],[-22.065,2.185],[-22.275,16.375],[-22.755,16.375],[-23.245,16.375],[-23.005,0.585],[-23.005,0.575],[-22.935,-4.415],[-22.845,-4.935],[-22.845,-4.945],[0.105,-15.815],[22.805,-5.415],[23.095,-4.575],[23.095,-4.495],[23.235,-3.935],[23.245,16.375]],"c":true},"ix":2},"nm":"Path 1","mn":"ADBE Vector Shape - Group","hd":false},{"ty":"fl","c":{"a":0,"k":[1,1,1,1],"ix":4},"o":{"a":0,"k":100,"ix":5},"r":1,"bm":0,"nm":"Fill 1","mn":"ADBE Vector Graphic - Fill","hd":false},{"ty":"tr","p":{"a":0,"k":[23.495,26.651],"ix":2},"a":{"a":0,"k":[0,0],"ix":1},"s":{"a":0,"k":[100,100],"ix":3},"r":{"a":0,"k":0,"ix":6},"o":{"a":0,"k":100,"ix":7},"sk":{"a":0,"k":0,"ix":4},"sa":{"a":0,"k":0,"ix":5},"nm":"Transform"}],"nm":"Group 7","np":2,"cix":2,"bm":0,"ix":7,"mn":"ADBE Vector Group","hd":false},{"ty":"gr","it":[{"ind":0,"ty":"sh","ix":1,"ks":{"a":0,"k":{"i":[[0,0],[0,0],[0,0],[0,0],[0,0],[0,0],[0,0],[-21.28,-0.64],[-0.79,-2.48],[0,0],[0,0],[0,0]],"o":[[0,0],[0,0],[0,0],[0,0],[0,0],[0,0],[0,0],[17.82,0.54],[0.15,0.48],[0,0],[0,0],[0,0]],"v":[[22.27,16.175],[-22.28,16.175],[-22.76,16.175],[-22.54,1.235],[-22.46,-4.125],[-22.46,-4.135],[-22.45,-4.605],[0.08,-15.535],[22.57,-4.845],[22.76,-4.075],[22.76,1.265],[22.76,16.175]],"c":true},"ix":2},"nm":"Path 1","mn":"ADBE Vector Shape - Group","hd":false},{"ty":"fl","c":{"a":0,"k":[1,0.580392156863,0.560784313725,1],"ix":4},"o":{"a":0,"k":100,"ix":5},"r":1,"bm":0,"nm":"Fill 1","mn":"ADBE Vector Graphic - Fill","hd":false},{"ty":"tr","p":{"a":0,"k":[23.5,26.851],"ix":2},"a":{"a":0,"k":[0,0],"ix":1},"s":{"a":0,"k":[100,100],"ix":3},"r":{"a":0,"k":0,"ix":6},"o":{"a":0,"k":100,"ix":7},"sk":{"a":0,"k":0,"ix":4},"sa":{"a":0,"k":0,"ix":5},"nm":"Transform"}],"nm":"Group 8","np":2,"cix":2,"bm":0,"ix":8,"mn":"ADBE Vector Group","hd":false}],"ip":0,"op":60,"st":0,"bm":0},{"ddd":0,"ind":10,"ty":4,"nm":"Frame","parent":4,"sr":1,"ks":{"o":{"a":0,"k":100,"ix":11},"r":{"a":0,"k":0,"ix":10},"p":{"a":0,"k":[49.778,88.977,0],"ix":2},"a":{"a":0,"k":[71.955,57.64,0],"ix":1},"s":{"a":0,"k":[100,100,100],"ix":6}},"ao":0,"shapes":[{"ty":"gr","it":[{"ind":0,"ty":"sh","ix":1,"ks":{"a":0,"k":{"i":[[0,0],[0,-4.56],[0,0],[0,0],[0,2.77],[0,0],[-2.77,0],[0,0],[0,-2.77],[0,0],[2.78,0],[0,0],[0,0],[4,1.58]],"o":[[-3.99,1.58],[0,0],[0,0],[-2.77,0],[0,0],[0,-2.77],[0,0],[2.78,0],[0,0],[0,2.77],[0,0],[0,0],[0,-4.56],[-4.434,-1.803]],"v":[[-4.005,-46.28],[-10.815,-36.24],[-10.815,17.33],[-62.835,17.33],[-67.855,12.31],[-67.855,-48.46],[-62.835,-53.48],[62.825,-53.48],[67.845,-48.46],[67.845,12.31],[62.825,17.33],[10.815,17.33],[10.815,-36.24],[3.995,-46.28]],"c":true},"ix":2},"nm":"Path 1","mn":"ADBE Vector Shape - Group","hd":false},{"ind":1,"ty":"sh","ix":2,"ks":{"a":0,"k":{"i":[[3.63,0],[0,0],[0,-3.63],[0,0],[-3.63,0],[0,0],[0,3.63],[0,0]],"o":[[0,0],[-3.63,0],[0,0],[0,3.63],[0,0],[3.63,0],[0,0],[0,-3.63]],"v":[[65.125,-57.39],[-65.135,-57.39],[-71.705,-50.82],[-71.705,50.82],[-65.135,57.39],[65.125,57.39],[71.705,50.82],[71.705,-50.82]],"c":true},"ix":2},"nm":"Path 2","mn":"ADBE Vector Shape - Group","hd":false},{"ty":"mm","mm":1,"nm":"Merge Paths 1","mn":"ADBE Vector Filter - Merge","hd":false},{"ty":"fl","c":{"a":0,"k":[0.949019667682,0.749019607843,0.498039245605,1],"ix":4},"o":{"a":0,"k":100,"ix":5},"r":1,"bm":0,"nm":"Fill 1","mn":"ADBE Vector Graphic - Fill","hd":false},{"ty":"tr","p":{"a":0,"k":[71.955,57.64],"ix":2},"a":{"a":0,"k":[0,0],"ix":1},"s":{"a":0,"k":[100,100],"ix":3},"r":{"a":0,"k":0,"ix":6},"o":{"a":0,"k":100,"ix":7},"sk":{"a":0,"k":0,"ix":4},"sa":{"a":0,"k":0,"ix":5},"nm":"Transform"}],"nm":"Group 1","np":4,"cix":2,"bm":0,"ix":1,"mn":"ADBE Vector Group","hd":false}],"ip":0,"op":60,"st":0,"bm":0},{"ddd":0,"ind":11,"ty":4,"nm":"Horizontal","parent":4,"sr":1,"ks":{"o":{"a":0,"k":100,"ix":11},"r":{"a":0,"k":0,"ix":10},"p":{"a":0,"k":[49.778,67.72,0],"ix":2},"a":{"a":0,"k":[68.102,2.769,0],"ix":1},"s":{"a":0,"k":[100,100,100],"ix":6}},"ao":0,"shapes":[{"ty":"gr","it":[{"ind":0,"ty":"sh","ix":1,"ks":{"a":0,"k":{"i":[[0,0],[0,0],[0,0],[0,0]],"o":[[0,0],[0,0],[0,0],[0,0]],"v":[[67.852,2.519],[-67.852,2.519],[-67.852,-2.519],[67.852,-2.519]],"c":true},"ix":2},"nm":"Path 1","mn":"ADBE Vector Shape - Group","hd":false},{"ty":"fl","c":{"a":0,"k":[0.949019667682,0.749019607843,0.498039245605,1],"ix":4},"o":{"a":0,"k":100,"ix":5},"r":1,"bm":0,"nm":"Fill 1","mn":"ADBE Vector Graphic - Fill","hd":false},{"ty":"tr","p":{"a":0,"k":[68.102,2.769],"ix":2},"a":{"a":0,"k":[0,0],"ix":1},"s":{"a":0,"k":[100,100],"ix":3},"r":{"a":0,"k":0,"ix":6},"o":{"a":0,"k":100,"ix":7},"sk":{"a":0,"k":0,"ix":4},"sa":{"a":0,"k":0,"ix":5},"nm":"Transform"}],"nm":"Group 1","np":2,"cix":2,"bm":0,"ix":1,"mn":"ADBE Vector Group","hd":false}],"ip":0,"op":60,"st":0,"bm":0},{"ddd":0,"ind":12,"ty":4,"nm":"Back 2","parent":4,"sr":1,"ks":{"o":{"a":0,"k":100,"ix":11},"r":{"a":0,"k":0,"ix":10},"p":{"a":0,"k":[49.776,36.756,0],"ix":2},"a":{"a":0,"k":[68.1,69.806,0],"ix":1},"s":{"a":0,"k":[100,100,100],"ix":6}},"ao":0,"shapes":[{"ty":"gr","it":[{"ind":0,"ty":"sh","ix":1,"ks":{"a":0,"k":{"i":[[0,0],[0,0],[5.973,0],[0,-5.973],[0,0],[0,0],[0,0],[0,0],[0,0]],"o":[[0,0],[0,-5.973],[-5.973,0],[0,0],[0,0],[0,0],[0,0],[0,0],[0,0]],"v":[[10.817,-1.256],[10.817,-58.742],[0.002,-69.557],[-10.813,-58.742],[-10.813,-1.256],[-67.85,-1.256],[-67.85,69.557],[67.85,69.557],[67.85,-1.256]],"c":true},"ix":2},"nm":"Path 1","mn":"ADBE Vector Shape - Group","hd":false},{"ty":"fl","c":{"a":0,"k":[0.607843137255,0.474509833841,0.329411764706,1],"ix":4},"o":{"a":0,"k":100,"ix":5},"r":1,"bm":0,"nm":"Fill 1","mn":"ADBE Vector Graphic - Fill","hd":false},{"ty":"tr","p":{"a":0,"k":[68.1,69.806],"ix":2},"a":{"a":0,"k":[0,0],"ix":1},"s":{"a":0,"k":[100,100],"ix":3},"r":{"a":0,"k":0,"ix":6},"o":{"a":0,"k":100,"ix":7},"sk":{"a":0,"k":0,"ix":4},"sa":{"a":0,"k":0,"ix":5},"nm":"Transform"}],"nm":"Group 1","np":2,"cix":2,"bm":0,"ix":1,"mn":"ADBE Vector Group","hd":false}],"ip":0,"op":60,"st":0,"bm":0}],"markers":[]}